Workbook

Sheet Decomposition
A1: SN ID | B1: Stakeholder requirement | C1: SLR ID | D1: System requirement (the NAS shall) | E1: HLR ID | F1: Sub-system HLR (constituent system shall) | G1: Objectives Addressed | H1: Review notes
A2: Stakeholder: Airline
A3: SN-AIR-01 | B3: The NAS shall provide a means for the airline to plan and fly each flight on the route, altitude and speed it chooses. | C3: SLR-PLN-01 | D3: The NAS shall produce for each scheduled flight a flight plan that states its route, cruise altitude, cruise speed and fuel load. (also answers SN-CRW-02) | E3: HLR-OPS-01 | F3: Flight operations shall plan each flight's route, cruise altitude, cruise speed and fuel load from a model of the performance of the aircraft assigned to it, with the fuel reserve the operating rules require. (also comes from SLR-PLN-02, SLR-PLN-04) | G3: {=IF(A3="","",_xlfn.TEXTJOIN(", ",TRUE,_xlfn._xlws.FILTER(Objectives!B$2:B$1000,ISNUMBER(SEARCH(A3,Objectives!D$2:D$1000)),"")))} -> Fuel cost, Crew cost, Maintenance, Delay cost, Revenue, Ticket price, Schedule convenience, Comfort, Operational flexibility, CO2, NOx, Contrail/climate effects, Noise, Local air quality
C4: SLR-PLN-02 | D4: The NAS shall compute each flight plan from the performance of the aircraft assigned to the flight. | E4: HLR-OPS-01 | F4: Flight operations shall plan each flight's route, cruise altitude, cruise speed and fuel load from a model of the performance of the aircraft assigned to it, with the fuel reserve the operating rules require. (also comes from SLR-PLN-01, SLR-PLN-04) | G4: {=IF(A4="","",_xlfn.TEXTJOIN(", ",TRUE,_xlfn._xlws.FILTER(Objectives!B$2:B$1000,ISNUMBER(SEARCH(A4,Objectives!D$2:D$1000)),"")))}
C5: SLR-CLR-09 | D5: The NAS shall answer each flight crew request for a route, altitude or speed change with an approval, an amended clearance or a refusal. (also answers SN-CRW-04, SN-PAX-03) | E5: HLR-CRW-03 | F5: The flight crew shall ask air traffic control for a change of route, altitude or speed when the crew deems it beneficial, optionally in collaboration with the dispatcher. (also comes from SLR-EXE-03) | G5: {=IF(A5="","",_xlfn.TEXTJOIN(", ",TRUE,_xlfn._xlws.FILTER(Objectives!B$2:B$1000,ISNUMBER(SEARCH(A5,Objectives!D$2:D$1000)),"")))}
E6: HLR-ATC-07 | F6: Air traffic control shall answer each flight crew request for a route, altitude or speed change with an approval, an amended clearance or 'unable'. | G6: {=IF(A6="","",_xlfn.TEXTJOIN(", ",TRUE,_xlfn._xlws.FILTER(Objectives!B$2:B$1000,ISNUMBER(SEARCH(A6,Objectives!D$2:D$1000)),"")))}
C7: SLR-EXE-03 | D7: The NAS shall predict each flight's arrival time, fuel at destination, optimum altitude and maximum altitude from the aircraft's estimated performance. (also answers SN-CRW-03) | E7: HLR-CRW-03 | F7: The flight crew shall ask air traffic control for a change of route, altitude or speed when the crew deems it beneficial, optionally in collaboration with the dispatcher. (also comes from SLR-CLR-09) | G7: {=IF(A7="","",_xlfn.TEXTJOIN(", ",TRUE,_xlfn._xlws.FILTER(Objectives!B$2:B$1000,ISNUMBER(SEARCH(A7,Objectives!D$2:D$1000)),"")))}
E8: HLR-CRW-05 | F8: The flight crew shall enter the load sheet weights and the released cost index into the flight management system before departure. (also comes from SLR-PLN-07) | G8: {=IF(A8="","",_xlfn.TEXTJOIN(", ",TRUE,_xlfn._xlws.FILTER(Objectives!B$2:B$1000,ISNUMBER(SEARCH(A8,Objectives!D$2:D$1000)),"")))}
E9: HLR-ACF-01 | F9: The flight management system shall predict the flight's arrival time, fuel at the destination, optimum altitude and maximum altitude from the entered weights, the cost index and the forecast winds. | G9: {=IF(A9="","",_xlfn.TEXTJOIN(", ",TRUE,_xlfn._xlws.FILTER(Objectives!B$2:B$1000,ISNUMBER(SEARCH(A9,Objectives!D$2:D$1000)),"")))}
E10: HLR-ACF-05 | F10: The flight management system shall make its current gross weight and its predicted optimum and maximum altitudes available for sharing with the party that decides, whether through the airline's systems or air traffic control's. (also comes from SLR-INF-02) | G10: {=IF(A10="","",_xlfn.TEXTJOIN(", ",TRUE,_xlfn._xlws.FILTER(Objectives!B$2:B$1000,ISNUMBER(SEARCH(A10,Objectives!D$2:D$1000)),"")))}
C11: SLR-MEA-02 | D11: The NAS shall report the fuel burned and the CO2 emitted by each flight, at 3.16 kg of CO2 per kg of fuel. (also answers SN-ENV-01) | E11: HLR-OPS-07 | F11: Flight operations shall report each flight's fuel burned and its CO2 emitted at 3.16 kg of CO2 per kg of fuel. | G11: {=IF(A11="","",_xlfn.TEXTJOIN(", ",TRUE,_xlfn._xlws.FILTER(Objectives!B$2:B$1000,ISNUMBER(SEARCH(A11,Objectives!D$2:D$1000)),"")))}
A12: SN-AIR-02 | B12: The NAS shall provide a means for each flight to achieve arrival at its destination gate at its scheduled arrival time. | C12: SLR-INF-07 | D12: The NAS shall send the airline and the destination airport an updated arrival estimate whenever a flight's estimate changes by more than 5 minutes. (also answers SN-AIR-03, SN-APT-01) | E12: HLR-CRW-04 | F12: The flight crew shall tell the dispatcher of each change to the cleared trajectory. (also comes from SLR-EXE-06, SLR-CLR-04) | G12: {=IF(A12="","",_xlfn.TEXTJOIN(", ",TRUE,_xlfn._xlws.FILTER(Objectives!B$2:B$1000,ISNUMBER(SEARCH(A12,Objectives!D$2:D$1000)),"")))} -> Aircraft utilization, Schedule integrity, Passenger connections, Dispatch reliability, Travel time, Connection reliability, Disruption risk, Predictability, Delay (ATC-attributed), Gate utilization, Runway utilization, Surface congestion, Turnaround performance, Passenger throughput, Schedule/duty constraints
E13: HLR-OPS-06 | F13: The dispatcher shall re-plan the flight with its crew when a trajectory change puts the arrival time, the fuel at the destination or flight safety at risk. (also comes from SLR-CLR-04, SLR-EXE-06) | G13: {=IF(A13="","",_xlfn.TEXTJOIN(", ",TRUE,_xlfn._xlws.FILTER(Objectives!B$2:B$1000,ISNUMBER(SEARCH(A13,Objectives!D$2:D$1000)),"")))}
C14: SLR-APT-01 | D14: [OUT OF STUDY] The NAS shall assign each arriving flight a gate before it lands. (also answers SN-APT-01) | F14: (no HLR: not carried into the study) | G14: {=IF(A14="","",_xlfn.TEXTJOIN(", ",TRUE,_xlfn._xlws.FILTER(Objectives!B$2:B$1000,ISNUMBER(SEARCH(A14,Objectives!D$2:D$1000)),"")))}
C15: SLR-APT-04 | D15: The NAS shall have each aircraft fuelled, loaded and sealed by its scheduled off- block time. | E15: HLR-APT-01 | F15: Airport operations shall have each aircraft fuelled, loaded and sealed by its scheduled off-block time. | G15: {=IF(A15="","",_xlfn.TEXTJOIN(", ",TRUE,_xlfn._xlws.FILTER(Objectives!B$2:B$1000,ISNUMBER(SEARCH(A15,Objectives!D$2:D$1000)),"")))}
E16: HLR-APT-02 | F16: Airport operations shall report the fuel uplifted and the load put on board to the flight crew and the load planner before off-block. (also comes from SLR-PLN-07) | G16: {=IF(A16="","",_xlfn.TEXTJOIN(", ",TRUE,_xlfn._xlws.FILTER(Objectives!B$2:B$1000,ISNUMBER(SEARCH(A16,Objectives!D$2:D$1000)),"")))}
C17: SLR-MEA-03 | D17: [OUT OF STUDY] The NAS shall report each flight's gate arrival time against its scheduled arrival time. (also answers SN-PAX-02) | F17: (no HLR: not carried into the study) | G17: {=IF(A17="","",_xlfn.TEXTJOIN(", ",TRUE,_xlfn._xlws.FILTER(Objectives!B$2:B$1000,ISNUMBER(SEARCH(A17,Objectives!D$2:D$1000)),"")))}
A18: SN-AIR-03 | B18: The NAS shall inform the airline of airspace and airport constraints that will delay or reroute its flights early enough for the airline to re-plan. | C18: SLR-FLW-07 | D18: [OUT OF STUDY] The NAS shall give traffic flow managers and airlines the activation schedule of special use airspace before the affected flight plans are filed. (also answers SN-MIL-01) | F18: (no HLR: not carried into the study) | G18: {=IF(A18="","",_xlfn.TEXTJOIN(", ",TRUE,_xlfn._xlws.FILTER(Objectives!B$2:B$1000,ISNUMBER(SEARCH(A18,Objectives!D$2:D$1000)),"")))} -> Schedule integrity, Delay cost
C19: SLR-CLR-04 | D19: The NAS shall provide a two-way communication path from the flight crew to the controlling facility and to the dispatcher for the whole flight. (also answers SN-CRW-08) | E19: HLR-CRW-04 | F19: The flight crew shall tell the dispatcher of each change to the cleared trajectory. (also comes from SLR-INF-07, SLR-EXE-06) | G19: {=IF(A19="","",_xlfn.TEXTJOIN(", ",TRUE,_xlfn._xlws.FILTER(Objectives!B$2:B$1000,ISNUMBER(SEARCH(A19,Objectives!D$2:D$1000)),"")))}
E20: HLR-OPS-06 | F20: The dispatcher shall re-plan the flight with its crew when a trajectory change puts the arrival time, the fuel at the destination or flight safety at risk. (also comes from SLR-INF-07, SLR-EXE-06) | G20: {=IF(A20="","",_xlfn.TEXTJOIN(", ",TRUE,_xlfn._xlws.FILTER(Objectives!B$2:B$1000,ISNUMBER(SEARCH(A20,Objectives!D$2:D$1000)),"")))}
E21: HLR-ACF-04 | F21: The aircraft communication system shall carry voice and data between the flight crew and both air traffic control and the dispatcher for the whole flight. | G21: {=IF(A21="","",_xlfn.TEXTJOIN(", ",TRUE,_xlfn._xlws.FILTER(Objectives!B$2:B$1000,ISNUMBER(SEARCH(A21,Objectives!D$2:D$1000)),"")))}
C22: SLR-INF-07 | D22: The NAS shall send the airline and the destination airport an updated arrival estimate whenever a flight's estimate changes by more than 5 minutes. (also answers SN-AIR-02, SN-APT-01) | E22: HLR-CRW-04 | F22: The flight crew shall tell the dispatcher of each change to the cleared trajectory. (also comes from SLR-EXE-06, SLR-CLR-04) | G22: {=IF(A22="","",_xlfn.TEXTJOIN(", ",TRUE,_xlfn._xlws.FILTER(Objectives!B$2:B$1000,ISNUMBER(SEARCH(A22,Objectives!D$2:D$1000)),"")))}
E23: HLR-OPS-06 | F23: The dispatcher shall re-plan the flight with its crew when a trajectory change puts the arrival time, the fuel at the destination or flight safety at risk. (also comes from SLR-CLR-04, SLR-EXE-06) | G23: {=IF(A23="","",_xlfn.TEXTJOIN(", ",TRUE,_xlfn._xlws.FILTER(Objectives!B$2:B$1000,ISNUMBER(SEARCH(A23,Objectives!D$2:D$1000)),"")))}
A24: SN-AIR-04 | B24: [OUT OF STUDY] The NAS shall let the airline choose which of its own flights takes a delay that the airline has been assigned. | C24: SLR-FLW-04 | D24: [OUT OF STUDY] The NAS shall let an airline exchange its own flights among the departure slots it has been assigned. | F24: (no HLR: not carried into the study) | G24: {=IF(A24="","",_xlfn.TEXTJOIN(", ",TRUE,_xlfn._xlws.FILTER(Objectives!B$2:B$1000,ISNUMBER(SEARCH(A24,Objectives!D$2:D$1000)),"")))}
A25: SN-AIR-05 | B25: The NAS shall take the airline's priorities for a flight (fuel against time, and protected connections) into account when a change to that flight's trajectory is required. | C25: SLR-CLR-13 | D25: [GOAL, IMPROVED] The NAS should choose, among the maneuvers that restore separation, the one with the lowest impact on the aircraft involved. (also answers SN-ENV-01) | E25: HLR-ATC-05 | F25: [GOAL, IMPROVED] Air traffic control should choose, among the clearances that resolve a conflict and can be flown, the one with the lowest impact on the systems involved. | G25: {=IF(A25="","",_xlfn.TEXTJOIN(", ",TRUE,_xlfn._xlws.FILTER(Objectives!B$2:B$1000,ISNUMBER(SEARCH(A25,Objectives!D$2:D$1000)),"")))} -> Fuel cost, Schedule integrity, Passenger connections, Operational flexibility, CO2, NOx, Contrail/climate effects, Noise, Local air quality
C26: SLR-INF-02 | D26: [IMPROVED] The NAS shall give the party that decides a change to an aircraft's trajectory the information needed to preserve safety and pursue optimality. (also answers SN-CRW-03) | E26: HLR-OPS-05 | F26: [IMPROVED] Flight operations shall make each flight's current gross weight, performance model, relative cost of flight time and connection priority available to the party that decides a change to that flight's trajectory. | G26: {=IF(A26="","",_xlfn.TEXTJOIN(", ",TRUE,_xlfn._xlws.FILTER(Objectives!B$2:B$1000,ISNUMBER(SEARCH(A26,Objectives!D$2:D$1000)),"")))}
E27: HLR-ATC-08 | F27: [IMPROVED] ATC decision support shall use the best information available to it about each flight, including the gross weight, performance model, relative cost of flight time and connection priority the airline has shared, to judge which clearances the aircraft can fly and what each costs. | G27: {=IF(A27="","",_xlfn.TEXTJOIN(", ",TRUE,_xlfn._xlws.FILTER(Objectives!B$2:B$1000,ISNUMBER(SEARCH(A27,Objectives!D$2:D$1000)),"")))}
E28: HLR-ACF-05 | F28: The flight management system shall make its current gross weight and its predicted optimum and maximum altitudes available for sharing with the party that decides, whether through the airline's systems or air traffic control's. (also comes from SLR-EXE-03) | G28: {=IF(A28="","",_xlfn.TEXTJOIN(", ",TRUE,_xlfn._xlws.FILTER(Objectives!B$2:B$1000,ISNUMBER(SEARCH(A28,Objectives!D$2:D$1000)),"")))}
A29: SN-AIR-06 | B29: [OUT OF STUDY] The NAS shall keep the airline's commercially sensitive flight data (aircraft weight, cost index, connection priorities) private. | C29: SLR-INF-05 | D29: [OUT OF STUDY] The NAS shall disclose an airline's shared weight, cost index and connection priority only to the parties deciding that flight's trajectory. | F29: (no HLR: not carried into the study) | G29: {=IF(A29="","",_xlfn.TEXTJOIN(", ",TRUE,_xlfn._xlws.FILTER(Objectives!B$2:B$1000,ISNUMBER(SEARCH(A29,Objectives!D$2:D$1000)),"")))}
A30: Stakeholder: Air traffic control | G30: {=IF(A30="","",_xlfn.TEXTJOIN(", ",TRUE,_xlfn._xlws.FILTER(Objectives!B$2:B$1000,ISNUMBER(SEARCH(A30,Objectives!D$2:D$1000)),"")))}
A31: SN-ATC-01 | B31: The NAS shall keep every controlled aircraft separated from every other aircraft by at least the applicable separation minimum. | C31: SLR-PLN-06 | D31: The NAS shall file each flight plan with air traffic control before the flight departs. (also answers SN-ATC-02, SN-ATC-03) | E31: HLR-OPS-02 | F31: The dispatcher shall file each flight's plan with air traffic control before departure. | G31: {=IF(A31="","",_xlfn.TEXTJOIN(", ",TRUE,_xlfn._xlws.FILTER(Objectives!B$2:B$1000,ISNUMBER(SEARCH(A31,Objectives!D$2:D$1000)),"")))} -> Flight Safety, Safety/separation
C32: SLR-CLR-01 | D32: The NAS shall keep each pair of controlled aircraft separated by at least the minimum that JO 7110.65BB sets for the airspace they are in. (also answers SN-CRW-06, SN-PAX-01) | E32: HLR-ATC-01 | F32: Air traffic control shall keep each pair of aircraft it controls separated by at least the applicable minimum, allowing for each aircraft's permitted deviation from its cleared route, altitude and speed. (also comes from SLR-EXE-02) | G32: {=IF(A32="","",_xlfn.TEXTJOIN(", ",TRUE,_xlfn._xlws.FILTER(Objectives!B$2:B$1000,ISNUMBER(SEARCH(A32,Objectives!D$2:D$1000)),"")))}
E33: HLR-ATC-04 | F33: [IMPROVED] Air traffic control shall resolve each predicted conflict with a clearance that every aircraft it moves can fly. (also comes from SLR-CLR-10) | G33: {=IF(A33="","",_xlfn.TEXTJOIN(", ",TRUE,_xlfn._xlws.FILTER(Objectives!B$2:B$1000,ISNUMBER(SEARCH(A33,Objectives!D$2:D$1000)),"")))}
E34: HLR-ACF-06 | F34: The aircraft's surveillance system shall broadcast the aircraft's position, altitude, velocity and identity by ADS-B Out. (also comes from SLR-CLR-02) | G34: {=IF(A34="","",_xlfn.TEXTJOIN(", ",TRUE,_xlfn._xlws.FILTER(Objectives!B$2:B$1000,ISNUMBER(SEARCH(A34,Objectives!D$2:D$1000)),"")))}
C35: SLR-CLR-02 | D35: The NAS shall predict a loss of separation between controlled aircraft before it occurs. (also answers SN-CRW-06) | E35: HLR-ATC-02 | F35: ATC decision support shall alert the sector controller to each predicted loss of separation before it occurs. | G35: {=IF(A35="","",_xlfn.TEXTJOIN(", ",TRUE,_xlfn._xlws.FILTER(Objectives!B$2:B$1000,ISNUMBER(SEARCH(A35,Objectives!D$2:D$1000)),"")))}
E36: HLR-ACF-06 | F36: The aircraft's surveillance system shall broadcast the aircraft's position, altitude, velocity and identity by ADS-B Out. (also comes from SLR-CLR-01) | G36: {=IF(A36="","",_xlfn.TEXTJOIN(", ",TRUE,_xlfn._xlws.FILTER(Objectives!B$2:B$1000,ISNUMBER(SEARCH(A36,Objectives!D$2:D$1000)),"")))}
C37: SLR-CLR-03 | D37: [OUT OF STUDY] The NAS shall give the controlling facility the position, altitude and identity of each controlled aircraft. (also answers SN-ATC-03) | F37: (no HLR: not carried into the study) | G37: {=IF(A37="","",_xlfn.TEXTJOIN(", ",TRUE,_xlfn._xlws.FILTER(Objectives!B$2:B$1000,ISNUMBER(SEARCH(A37,Objectives!D$2:D$1000)),"")))}
C38: SLR-CLR-05 | D38: [OUT OF STUDY] The NAS shall change a controlled aircraft's cleared route, altitude or speed only by a clearance from the facility that has control of that aircraft. (also answers SN-GOV-02) | F38: (no HLR: not carried into the study) | G38: {=IF(A38="","",_xlfn.TEXTJOIN(", ",TRUE,_xlfn._xlws.FILTER(Objectives!B$2:B$1000,ISNUMBER(SEARCH(A38,Objectives!D$2:D$1000)),"")))}
C39: SLR-INF-01 | D39: The NAS shall give the sector controller the filed route, requested altitude and requested speed of each aircraft before it enters the sector. (also answers SN-ATC-03) | E39: HLR-ATC-03 | F39: The en-route center shall inform the sector controller of each aircraft's filed route, requested altitude and requested speed before the aircraft enters the sector. | G39: {=IF(A39="","",_xlfn.TEXTJOIN(", ",TRUE,_xlfn._xlws.FILTER(Objectives!B$2:B$1000,ISNUMBER(SEARCH(A39,Objectives!D$2:D$1000)),"")))}
C40: SLR-EXE-02 | D40: The NAS shall fly each aircraft along its cleared route and at its cleared altitude and speed within the navigation and altitude tolerances of the airspace. (also answers SN-ATC-03) | E40: HLR-CRW-01 | F40: The flight crew shall safely control the flight from origin to destination, as cleared by air traffic control with or without negotiation, and in collaboration with flight operations. (also comes from SLR-CLR-08, SLR-PLN-05) | G40: {=IF(A40="","",_xlfn.TEXTJOIN(", ",TRUE,_xlfn._xlws.FILTER(Objectives!B$2:B$1000,ISNUMBER(SEARCH(A40,Objectives!D$2:D$1000)),"")))}
E41: HLR-ATC-01 | F41: Air traffic control shall keep each pair of aircraft it controls separated by at least the applicable minimum, allowing for each aircraft's permitted deviation from its cleared route, altitude and speed. (also comes from SLR-CLR-01) | G41: {=IF(A41="","",_xlfn.TEXTJOIN(", ",TRUE,_xlfn._xlws.FILTER(Objectives!B$2:B$1000,ISNUMBER(SEARCH(A41,Objectives!D$2:D$1000)),"")))}
E42: HLR-ACF-02 | F42: The auto flight control system shall hold the aircraft on its cleared route, altitude and speed within the tolerances of the airspace. | G42: {=IF(A42="","",_xlfn.TEXTJOIN(", ",TRUE,_xlfn._xlws.FILTER(Objectives!B$2:B$1000,ISNUMBER(SEARCH(A42,Objectives!D$2:D$1000)),"")))}
A43: SN-ATC-02 | B43: The NAS shall keep the number of aircraft in each sector and at each airport within its declared capacity. | C43: SLR-PLN-06 | D43: The NAS shall file each flight plan with air traffic control before the flight departs. (also answers SN-ATC-01, SN-ATC-03) | E43: HLR-OPS-02 | F43: The dispatcher shall file each flight's plan with air traffic control before departure. | G43: {=IF(A43="","",_xlfn.TEXTJOIN(", ",TRUE,_xlfn._xlws.FILTER(Objectives!B$2:B$1000,ISNUMBER(SEARCH(A43,Objectives!D$2:D$1000)),"")))} -> Capacity
C44: SLR-PLN-08 | D44: [OUT OF STUDY] The NAS shall plan each flight to comply with the traffic management initiatives and special use airspace activations published for its time of flight. (also answers SN-MIL-01) | F44: (no HLR: not carried into the study) | G44: {=IF(A44="","",_xlfn.TEXTJOIN(", ",TRUE,_xlfn._xlws.FILTER(Objectives!B$2:B$1000,ISNUMBER(SEARCH(A44,Objectives!D$2:D$1000)),"")))}
C45: SLR-FLW-06 | D45: [OUT OF STUDY] The NAS shall release each flight that has an expect departure clearance time (EDCT) within the permitted window around that time. (also answers SN-ATC-03) | F45: (no HLR: not carried into the study) | G45: {=IF(A45="","",_xlfn.TEXTJOIN(", ",TRUE,_xlfn._xlws.FILTER(Objectives!B$2:B$1000,ISNUMBER(SEARCH(A45,Objectives!D$2:D$1000)),"")))}
C46: SLR-APT-02 | D46: [OUT OF STUDY] The NAS shall sequence arrivals and departures so that each runway is used at its declared capacity whenever demand is at or above that rate. (also answers SN-APT-02) | F46: (no HLR: not carried into the study) | G46: {=IF(A46="","",_xlfn.TEXTJOIN(", ",TRUE,_xlfn._xlws.FILTER(Objectives!B$2:B$1000,ISNUMBER(SEARCH(A46,Objectives!D$2:D$1000)),"")))}
A47: SN-ATC-03 | B47: [OUT OF STUDY] The NAS shall make the path each controlled aircraft will fly known to its controller in advance. | C47: SLR-PLN-06 | D47: The NAS shall file each flight plan with air traffic control before the flight departs. (also answers SN-ATC-01, SN-ATC-02) | E47: HLR-OPS-02 | F47: The dispatcher shall file each flight's plan with air traffic control before departure. | G47: {=IF(A47="","",_xlfn.TEXTJOIN(", ",TRUE,_xlfn._xlws.FILTER(Objectives!B$2:B$1000,ISNUMBER(SEARCH(A47,Objectives!D$2:D$1000)),"")))}
C48: SLR-FLW-06 | D48: [OUT OF STUDY] The NAS shall release each flight that has an expect departure clearance time (EDCT) within the permitted window around that time. (also answers SN-ATC-02) | F48: (no HLR: not carried into the study) | G48: {=IF(A48="","",_xlfn.TEXTJOIN(", ",TRUE,_xlfn._xlws.FILTER(Objectives!B$2:B$1000,ISNUMBER(SEARCH(A48,Objectives!D$2:D$1000)),"")))}
C49: SLR-CLR-03 | D49: [OUT OF STUDY] The NAS shall give the controlling facility the position, altitude and identity of each controlled aircraft. (also answers SN-ATC-01) | F49: (no HLR: not carried into the study) | G49: {=IF(A49="","",_xlfn.TEXTJOIN(", ",TRUE,_xlfn._xlws.FILTER(Objectives!B$2:B$1000,ISNUMBER(SEARCH(A49,Objectives!D$2:D$1000)),"")))}
C50: SLR-INF-01 | D50: The NAS shall give the sector controller the filed route, requested altitude and requested speed of each aircraft before it enters the sector. (also answers SN-ATC-01) | E50: HLR-ATC-03 | F50: The en-route center shall inform the sector controller of each aircraft's filed route, requested altitude and requested speed before the aircraft enters the sector. | G50: {=IF(A50="","",_xlfn.TEXTJOIN(", ",TRUE,_xlfn._xlws.FILTER(Objectives!B$2:B$1000,ISNUMBER(SEARCH(A50,Objectives!D$2:D$1000)),"")))}
C51: SLR-EXE-01 | D51: [OUT OF STUDY] The NAS shall hold each flight's cleared route and altitudes in the flight management system as the path the aircraft's guidance follows. | F51: (no HLR: not carried into the study) | G51: {=IF(A51="","",_xlfn.TEXTJOIN(", ",TRUE,_xlfn._xlws.FILTER(Objectives!B$2:B$1000,ISNUMBER(SEARCH(A51,Objectives!D$2:D$1000)),"")))}
C52: SLR-EXE-02 | D52: The NAS shall fly each aircraft along its cleared route and at its cleared altitude and speed within the navigation and altitude tolerances of the airspace. (also answers SN-ATC-01) | E52: HLR-CRW-01 | F52: The flight crew shall safely control the flight from origin to destination, as cleared by air traffic control with or without negotiation, and in collaboration with flight operations. (also comes from SLR-CLR-08, SLR-PLN-05) | G52: {=IF(A52="","",_xlfn.TEXTJOIN(", ",TRUE,_xlfn._xlws.FILTER(Objectives!B$2:B$1000,ISNUMBER(SEARCH(A52,Objectives!D$2:D$1000)),"")))}
E53: HLR-ATC-01 | F53: Air traffic control shall keep each pair of aircraft it controls separated by at least the applicable minimum, allowing for each aircraft's permitted deviation from its cleared route, altitude and speed. (also comes from SLR-CLR-01) | G53: {=IF(A53="","",_xlfn.TEXTJOIN(", ",TRUE,_xlfn._xlws.FILTER(Objectives!B$2:B$1000,ISNUMBER(SEARCH(A53,Objectives!D$2:D$1000)),"")))}
E54: HLR-ACF-02 | F54: The auto flight control system shall hold the aircraft on its cleared route, altitude and speed within the tolerances of the airspace. | G54: {=IF(A54="","",_xlfn.TEXTJOIN(", ",TRUE,_xlfn._xlws.FILTER(Objectives!B$2:B$1000,ISNUMBER(SEARCH(A54,Objectives!D$2:D$1000)),"")))}
A55: SN-ATC-04 | B55: The NAS shall keep the number of control actions a sector controller must take within what one sector team can sustain. | C55: SLR-CLR-15 | D55: The NAS shall keep the control instructions needed to resolve a conflict within what the sector team can sustain. | E55: HLR-ATC-06 | F55: Air traffic control shall resolve each predicted conflict within the number of instructions the sector team can sustain. | G55: {=IF(A55="","",_xlfn.TEXTJOIN(", ",TRUE,_xlfn._xlws.FILTER(Objectives!B$2:B$1000,ISNUMBER(SEARCH(A55,Objectives!D$2:D$1000)),"")))} -> Sector workload, Traffic complexity
A56: SN-ATC-05 | B56: [OUT OF STUDY] The NAS shall share unavoidable delay equitably among airspace users. | C56: SLR-FLW-05 | D56: [OUT OF STUDY] The NAS shall assign the delay created by a traffic management initiative equitably among all airspace users. | F56: (no HLR: not carried into the study) | G56: {=IF(A56="","",_xlfn.TEXTJOIN(", ",TRUE,_xlfn._xlws.FILTER(Objectives!B$2:B$1000,ISNUMBER(SEARCH(A56,Objectives!D$2:D$1000)),"")))}
C57: SLR-MEA-04 | D57: [OUT OF STUDY] The NAS shall report the delay each flight received from traffic management initiatives, by airline. | F57: (no HLR: not carried into the study) | G57: {=IF(A57="","",_xlfn.TEXTJOIN(", ",TRUE,_xlfn._xlws.FILTER(Objectives!B$2:B$1000,ISNUMBER(SEARCH(A57,Objectives!D$2:D$1000)),"")))}
A58: Stakeholder: Flight crew | G58: {=IF(A58="","",_xlfn.TEXTJOIN(", ",TRUE,_xlfn._xlws.FILTER(Objectives!B$2:B$1000,ISNUMBER(SEARCH(A58,Objectives!D$2:D$1000)),"")))}
A59: SN-CRW-01 | B59: [OUT OF STUDY] The NAS shall preserve the captain's final authority over the safe conduct of the flight. | C59: SLR-PLN-05 | D59: The NAS shall release a flight only when the dispatcher and the captain both agree that it can be flown safely as planned. (also answers SN-GOV-01, SN-GOV-02) | E59: HLR-CRW-01 | F59: The flight crew shall safely control the flight from origin to destination, as cleared by air traffic control with or without negotiation, and in collaboration with flight operations. (also comes from SLR-EXE-02, SLR-CLR-08) | G59: {=IF(A59="","",_xlfn.TEXTJOIN(", ",TRUE,_xlfn._xlws.FILTER(Objectives!B$2:B$1000,ISNUMBER(SEARCH(A59,Objectives!D$2:D$1000)),"")))}
E60: HLR-OPS-04 | F60: The dispatcher shall release a flight only with the captain's agreement that it can be flown safely as planned. | G60: {=IF(A60="","",_xlfn.TEXTJOIN(", ",TRUE,_xlfn._xlws.FILTER(Objectives!B$2:B$1000,ISNUMBER(SEARCH(A60,Objectives!D$2:D$1000)),"")))}
C61: SLR-CLR-08 | D61: The NAS shall allow the captain to deviate from a clearance when safety requires it, with air traffic control told as soon as practical. (also answers SN-GOV-01, SN-PAX-01) | E61: HLR-CRW-01 | F61: The flight crew shall safely control the flight from origin to destination, as cleared by air traffic control with or without negotiation, and in collaboration with flight operations. (also comes from SLR-EXE-02, SLR-PLN-05) | G61: {=IF(A61="","",_xlfn.TEXTJOIN(", ",TRUE,_xlfn._xlws.FILTER(Objectives!B$2:B$1000,ISNUMBER(SEARCH(A61,Objectives!D$2:D$1000)),"")))}
C62: SLR-EXE-04 | D62: [OUT OF STUDY] The NAS shall change an aircraft's flown trajectory only through flight deck controls operated by the flight crew. (also answers SN-GOV-02) | F62: (no HLR: not carried into the study) | G62: {=IF(A62="","",_xlfn.TEXTJOIN(", ",TRUE,_xlfn._xlws.FILTER(Objectives!B$2:B$1000,ISNUMBER(SEARCH(A62,Objectives!D$2:D$1000)),"")))}
A63: SN-CRW-02 | B63: [OUT OF STUDY] The NAS shall give the flight crew the information needed for each phase of flight before that phase begins. | C63: SLR-PLN-01 | D63: The NAS shall produce for each scheduled flight a flight plan that states its route, cruise altitude, cruise speed and fuel load. (also answers SN-AIR-01) | E63: HLR-OPS-01 | F63: Flight operations shall plan each flight's route, cruise altitude, cruise speed and fuel load from a model of the performance of the aircraft assigned to it, with the fuel reserve the operating rules require. (also comes from SLR-PLN-02, SLR-PLN-04) | G63: {=IF(A63="","",_xlfn.TEXTJOIN(", ",TRUE,_xlfn._xlws.FILTER(Objectives!B$2:B$1000,ISNUMBER(SEARCH(A63,Objectives!D$2:D$1000)),"")))}
C64: SLR-PLN-07 | D64: The NAS shall deliver the dispatch release, flight plan, weather, notices to airmen (NOTAMs) and load sheet to the flight crew before departure. (also answers SN-CRW-07) | E64: HLR-CRW-05 | F64: The flight crew shall enter the load sheet weights and the released cost index into the flight management system before departure. (also comes from SLR-EXE-03) | G64: {=IF(A64="","",_xlfn.TEXTJOIN(", ",TRUE,_xlfn._xlws.FILTER(Objectives!B$2:B$1000,ISNUMBER(SEARCH(A64,Objectives!D$2:D$1000)),"")))}
E65: HLR-OPS-03 | F65: Flight operations shall give the flight crew the dispatch release, flight plan, weather, notices to airmen (NOTAMs) and load sheet before departure. | G65: {=IF(A65="","",_xlfn.TEXTJOIN(", ",TRUE,_xlfn._xlws.FILTER(Objectives!B$2:B$1000,ISNUMBER(SEARCH(A65,Objectives!D$2:D$1000)),"")))}
E66: HLR-APT-02 | F66: Airport operations shall report the fuel uplifted and the load put on board to the flight crew and the load planner before off-block. (also comes from SLR-APT-04) | G66: {=IF(A66="","",_xlfn.TEXTJOIN(", ",TRUE,_xlfn._xlws.FILTER(Objectives!B$2:B$1000,ISNUMBER(SEARCH(A66,Objectives!D$2:D$1000)),"")))}
C67: SLR-INF-06 | D67: [OUT OF STUDY] The NAS shall give the dispatcher and the flight crew the reported and forecast weather and turbulence along the planned route. (also answers SN-PAX-03) | F67: (no HLR: not carried into the study) | G67: {=IF(A67="","",_xlfn.TEXTJOIN(", ",TRUE,_xlfn._xlws.FILTER(Objectives!B$2:B$1000,ISNUMBER(SEARCH(A67,Objectives!D$2:D$1000)),"")))}
C68: SLR-EXE-06 | D68: The NAS shall alert the flight crew, dispatchers and controllers when the fuel predicted at the destination falls below the required reserve. (also answers SN-GOV-01, SN-CRW-03, SN-PAX-01) | E68: HLR-CRW-04 | F68: The flight crew shall tell the dispatcher of each change to the cleared trajectory. (also comes from SLR-INF-07, SLR-CLR-04) | G68: {=IF(A68="","",_xlfn.TEXTJOIN(", ",TRUE,_xlfn._xlws.FILTER(Objectives!B$2:B$1000,ISNUMBER(SEARCH(A68,Objectives!D$2:D$1000)),"")))}
E69: HLR-OPS-06 | F69: The dispatcher shall re-plan the flight with its crew when a trajectory change puts the arrival time, the fuel at the destination or flight safety at risk. (also comes from SLR-CLR-04, SLR-INF-07) | G69: {=IF(A69="","",_xlfn.TEXTJOIN(", ",TRUE,_xlfn._xlws.FILTER(Objectives!B$2:B$1000,ISNUMBER(SEARCH(A69,Objectives!D$2:D$1000)),"")))}
E70: HLR-ACF-03 | F70: The flight management system shall alert the flight crew when the fuel it predicts at the destination falls below the required reserve. | G70: {=IF(A70="","",_xlfn.TEXTJOIN(", ",TRUE,_xlfn._xlws.FILTER(Objectives!B$2:B$1000,ISNUMBER(SEARCH(A70,Objectives!D$2:D$1000)),"")))}
A71: SN-CRW-03 | B71: The NAS shall give the flight crew only trajectory clearances and instructions that the aircraft can fly, with enough time to set them up. | C71: SLR-CLR-10 | D71: [IMPROVED] The NAS shall issue only clearances that the aircraft can fly. | E71: HLR-CRW-02 | F71: The flight crew shall accept a clearance only if the aircraft can fly it, and shall answer 'unable' when it cannot. | G71: {=IF(A71="","",_xlfn.TEXTJOIN(", ",TRUE,_xlfn._xlws.FILTER(Objectives!B$2:B$1000,ISNUMBER(SEARCH(A71,Objectives!D$2:D$1000)),"")))} -> Safety, Workload
E72: HLR-ATC-04 | F72: [IMPROVED] Air traffic control shall resolve each predicted conflict with a clearance that every aircraft it moves can fly. (also comes from SLR-CLR-01) | G72: {=IF(A72="","",_xlfn.TEXTJOIN(", ",TRUE,_xlfn._xlws.FILTER(Objectives!B$2:B$1000,ISNUMBER(SEARCH(A72,Objectives!D$2:D$1000)),"")))}
C73: SLR-INF-02 | D73: [IMPROVED] The NAS shall give the party that decides a change to an aircraft's trajectory the information needed to preserve safety and pursue optimality. (also answers SN-AIR-05) | E73: HLR-OPS-05 | F73: [IMPROVED] Flight operations shall make each flight's current gross weight, performance model, relative cost of flight time and connection priority available to the party that decides a change to that flight's trajectory. | G73: {=IF(A73="","",_xlfn.TEXTJOIN(", ",TRUE,_xlfn._xlws.FILTER(Objectives!B$2:B$1000,ISNUMBER(SEARCH(A73,Objectives!D$2:D$1000)),"")))}
E74: HLR-ATC-08 | F74: [IMPROVED] ATC decision support shall use the best information available to it about each flight, including the gross weight, performance model, relative cost of flight time and connection priority the airline has shared, to judge which clearances the aircraft can fly and what each costs. | G74: {=IF(A74="","",_xlfn.TEXTJOIN(", ",TRUE,_xlfn._xlws.FILTER(Objectives!B$2:B$1000,ISNUMBER(SEARCH(A74,Objectives!D$2:D$1000)),"")))}
E75: HLR-ACF-05 | F75: The flight management system shall make its current gross weight and its predicted optimum and maximum altitudes available for sharing with the party that decides, whether through the airline's systems or air traffic control's. (also comes from SLR-EXE-03) | G75: {=IF(A75="","",_xlfn.TEXTJOIN(", ",TRUE,_xlfn._xlws.FILTER(Objectives!B$2:B$1000,ISNUMBER(SEARCH(A75,Objectives!D$2:D$1000)),"")))}
C76: SLR-EXE-03 | D76: The NAS shall predict each flight's arrival time, fuel at destination, optimum altitude and maximum altitude from the aircraft's estimated performance. (also answers SN-AIR-01) | E76: HLR-CRW-03 | F76: The flight crew shall ask air traffic control for a change of route, altitude or speed when the crew deems it beneficial, optionally in collaboration with the dispatcher. (also comes from SLR-CLR-09) | G76: {=IF(A76="","",_xlfn.TEXTJOIN(", ",TRUE,_xlfn._xlws.FILTER(Objectives!B$2:B$1000,ISNUMBER(SEARCH(A76,Objectives!D$2:D$1000)),"")))}
E77: HLR-CRW-05 | F77: The flight crew shall enter the load sheet weights and the released cost index into the flight management system before departure. (also comes from SLR-PLN-07) | G77: {=IF(A77="","",_xlfn.TEXTJOIN(", ",TRUE,_xlfn._xlws.FILTER(Objectives!B$2:B$1000,ISNUMBER(SEARCH(A77,Objectives!D$2:D$1000)),"")))}
E78: HLR-ACF-01 | F78: The flight management system shall predict the flight's arrival time, fuel at the destination, optimum altitude and maximum altitude from the entered weights, the cost index and the forecast winds. | G78: {=IF(A78="","",_xlfn.TEXTJOIN(", ",TRUE,_xlfn._xlws.FILTER(Objectives!B$2:B$1000,ISNUMBER(SEARCH(A78,Objectives!D$2:D$1000)),"")))}
E79: HLR-ACF-05 | F79: The flight management system shall make its current gross weight and its predicted optimum and maximum altitudes available for sharing with the party that decides, whether through the airline's systems or air traffic control's. (also comes from SLR-INF-02) | G79: {=IF(A79="","",_xlfn.TEXTJOIN(", ",TRUE,_xlfn._xlws.FILTER(Objectives!B$2:B$1000,ISNUMBER(SEARCH(A79,Objectives!D$2:D$1000)),"")))}
C80: SLR-EXE-06 | D80: The NAS shall alert the flight crew, dispatchers and controllers when the fuel predicted at the destination falls below the required reserve. (also answers SN-GOV-01, SN-PAX-01, SN-CRW-02) | E80: HLR-CRW-04 | F80: The flight crew shall tell the dispatcher of each change to the cleared trajectory. (also comes from SLR-INF-07, SLR-CLR-04) | G80: {=IF(A80="","",_xlfn.TEXTJOIN(", ",TRUE,_xlfn._xlws.FILTER(Objectives!B$2:B$1000,ISNUMBER(SEARCH(A80,Objectives!D$2:D$1000)),"")))}
E81: HLR-OPS-06 | F81: The dispatcher shall re-plan the flight with its crew when a trajectory change puts the arrival time, the fuel at the destination or flight safety at risk. (also comes from SLR-CLR-04, SLR-INF-07) | G81: {=IF(A81="","",_xlfn.TEXTJOIN(", ",TRUE,_xlfn._xlws.FILTER(Objectives!B$2:B$1000,ISNUMBER(SEARCH(A81,Objectives!D$2:D$1000)),"")))}
E82: HLR-ACF-03 | F82: The flight management system shall alert the flight crew when the fuel it predicts at the destination falls below the required reserve. | G82: {=IF(A82="","",_xlfn.TEXTJOIN(", ",TRUE,_xlfn._xlws.FILTER(Objectives!B$2:B$1000,ISNUMBER(SEARCH(A82,Objectives!D$2:D$1000)),"")))}
A83: SN-CRW-04 | B83: [OUT OF STUDY] The NAS shall let the flight crew ask for a trajectory change and get an answer. | C83: SLR-CLR-09 | D83: The NAS shall answer each flight crew request for a route, altitude or speed change with an approval, an amended clearance or a refusal. (also answers SN-AIR-01, SN-PAX-03) | E83: HLR-CRW-03 | F83: The flight crew shall ask air traffic control for a change of route, altitude or speed when the crew deems it beneficial, optionally in collaboration with the dispatcher. (also comes from SLR-EXE-03) | G83: {=IF(A83="","",_xlfn.TEXTJOIN(", ",TRUE,_xlfn._xlws.FILTER(Objectives!B$2:B$1000,ISNUMBER(SEARCH(A83,Objectives!D$2:D$1000)),"")))}
E84: HLR-ATC-07 | F84: Air traffic control shall answer each flight crew request for a route, altitude or speed change with an approval, an amended clearance or 'unable'. | G84: {=IF(A84="","",_xlfn.TEXTJOIN(", ",TRUE,_xlfn._xlws.FILTER(Objectives!B$2:B$1000,ISNUMBER(SEARCH(A84,Objectives!D$2:D$1000)),"")))}
A85: SN-CRW-05 | B85: [OUT OF STUDY] The NAS shall keep each flight crew member within flight and duty time limits. | C85: SLR-PLN-09 | D85: [OUT OF STUDY] The NAS shall assign to each flight a crew whose duty period, including forecast delay, stays within the limits of 14 CFR Part 117. (also answers SN-GOV-01) | F85: (no HLR: not carried into the study) | G85: {=IF(A85="","",_xlfn.TEXTJOIN(", ",TRUE,_xlfn._xlws.FILTER(Objectives!B$2:B$1000,ISNUMBER(SEARCH(A85,Objectives!D$2:D$1000)),"")))}
A86: SN-CRW-06 | B86: The NAS shall provide the flight crew clearances that account for air traffic. | C86: SLR-CLR-01 | D86: The NAS shall keep each pair of controlled aircraft separated by at least the minimum that JO 7110.65BB sets for the airspace they are in. (also answers SN-ATC-01, SN-PAX-01) | E86: HLR-ATC-01 | F86: Air traffic control shall keep each pair of aircraft it controls separated by at least the applicable minimum, allowing for each aircraft's permitted deviation from its cleared route, altitude and speed. (also comes from SLR-EXE-02) | G86: {=IF(A86="","",_xlfn.TEXTJOIN(", ",TRUE,_xlfn._xlws.FILTER(Objectives!B$2:B$1000,ISNUMBER(SEARCH(A86,Objectives!D$2:D$1000)),"")))} -> Safety
E87: HLR-ATC-04 | F87: [IMPROVED] Air traffic control shall resolve each predicted conflict with a clearance that every aircraft it moves can fly. (also comes from SLR-CLR-10) | G87: {=IF(A87="","",_xlfn.TEXTJOIN(", ",TRUE,_xlfn._xlws.FILTER(Objectives!B$2:B$1000,ISNUMBER(SEARCH(A87,Objectives!D$2:D$1000)),"")))}
E88: HLR-ACF-06 | F88: The aircraft's surveillance system shall broadcast the aircraft's position, altitude, velocity and identity by ADS-B Out. (also comes from SLR-CLR-02) | G88: {=IF(A88="","",_xlfn.TEXTJOIN(", ",TRUE,_xlfn._xlws.FILTER(Objectives!B$2:B$1000,ISNUMBER(SEARCH(A88,Objectives!D$2:D$1000)),"")))}
C89: SLR-CLR-02 | D89: The NAS shall predict a loss of separation between controlled aircraft before it occurs. (also answers SN-ATC-01) | E89: HLR-ATC-02 | F89: ATC decision support shall alert the sector controller to each predicted loss of separation before it occurs. | G89: {=IF(A89="","",_xlfn.TEXTJOIN(", ",TRUE,_xlfn._xlws.FILTER(Objectives!B$2:B$1000,ISNUMBER(SEARCH(A89,Objectives!D$2:D$1000)),"")))}
E90: HLR-ACF-06 | F90: The aircraft's surveillance system shall broadcast the aircraft's position, altitude, velocity and identity by ADS-B Out. (also comes from SLR-CLR-01) | G90: {=IF(A90="","",_xlfn.TEXTJOIN(", ",TRUE,_xlfn._xlws.FILTER(Objectives!B$2:B$1000,ISNUMBER(SEARCH(A90,Objectives!D$2:D$1000)),"")))}
A91: SN-CRW-07 | B91: The NAS shall inform the flight crew of weather, traffic and other safety considerations. | C91: SLR-PLN-07 | D91: The NAS shall deliver the dispatch release, flight plan, weather, notices to airmen (NOTAMs) and load sheet to the flight crew before departure. (also answers SN-CRW-02) | E91: HLR-CRW-05 | F91: The flight crew shall enter the load sheet weights and the released cost index into the flight management system before departure. (also comes from SLR-EXE-03) | G91: {=IF(A91="","",_xlfn.TEXTJOIN(", ",TRUE,_xlfn._xlws.FILTER(Objectives!B$2:B$1000,ISNUMBER(SEARCH(A91,Objectives!D$2:D$1000)),"")))} -> Safety, Procedural compliance
E92: HLR-OPS-03 | F92: Flight operations shall give the flight crew the dispatch release, flight plan, weather, notices to airmen (NOTAMs) and load sheet before departure. | G92: {=IF(A92="","",_xlfn.TEXTJOIN(", ",TRUE,_xlfn._xlws.FILTER(Objectives!B$2:B$1000,ISNUMBER(SEARCH(A92,Objectives!D$2:D$1000)),"")))}
E93: HLR-APT-02 | F93: Airport operations shall report the fuel uplifted and the load put on board to the flight crew and the load planner before off-block. (also comes from SLR-APT-04) | G93: {=IF(A93="","",_xlfn.TEXTJOIN(", ",TRUE,_xlfn._xlws.FILTER(Objectives!B$2:B$1000,ISNUMBER(SEARCH(A93,Objectives!D$2:D$1000)),"")))}
A94: SN-CRW-08 | B94: The NAS shall facilitate control of the aircraft across regional sectors, coordinating controls, clearances and handoffs. | C94: SLR-CLR-04 | D94: The NAS shall provide a two-way communication path from the flight crew to the controlling facility and to the dispatcher for the whole flight. (also answers SN-AIR-03) | E94: HLR-CRW-04 | F94: The flight crew shall tell the dispatcher of each change to the cleared trajectory. (also comes from SLR-INF-07, SLR-EXE-06) | G94: {=IF(A94="","",_xlfn.TEXTJOIN(", ",TRUE,_xlfn._xlws.FILTER(Objectives!B$2:B$1000,ISNUMBER(SEARCH(A94,Objectives!D$2:D$1000)),"")))} -> Workload, Procedural compliance
E95: HLR-OPS-06 | F95: The dispatcher shall re-plan the flight with its crew when a trajectory change puts the arrival time, the fuel at the destination or flight safety at risk. (also comes from SLR-INF-07, SLR-EXE-06) | G95: {=IF(A95="","",_xlfn.TEXTJOIN(", ",TRUE,_xlfn._xlws.FILTER(Objectives!B$2:B$1000,ISNUMBER(SEARCH(A95,Objectives!D$2:D$1000)),"")))}
E96: HLR-ACF-04 | F96: The aircraft communication system shall carry voice and data between the flight crew and both air traffic control and the dispatcher for the whole flight. | G96: {=IF(A96="","",_xlfn.TEXTJOIN(", ",TRUE,_xlfn._xlws.FILTER(Objectives!B$2:B$1000,ISNUMBER(SEARCH(A96,Objectives!D$2:D$1000)),"")))}
A97: Stakeholder: Regulator | G97: {=IF(A97="","",_xlfn.TEXTJOIN(", ",TRUE,_xlfn._xlws.FILTER(Objectives!B$2:B$1000,ISNUMBER(SEARCH(A97,Objectives!D$2:D$1000)),"")))}
A98: SN-GOV-01 | B98: [BACKGROUND] The NAS shall conduct every flight within the operating rules of 14 CFR and the FAA's air traffic orders. | C98: SLR-PLN-04 | D98: The NAS shall load each flight with fuel to reach its destination, then its most distant alternate, then fly 45 minutes at normal cruise. (also answers SN-PAX-01) | E98: HLR-OPS-01 | F98: Flight operations shall plan each flight's route, cruise altitude, cruise speed and fuel load from a model of the performance of the aircraft assigned to it, with the fuel reserve the operating rules require. (also comes from SLR-PLN-01, SLR-PLN-02) | G98: {=IF(A98="","",_xlfn.TEXTJOIN(", ",TRUE,_xlfn._xlws.FILTER(Objectives!B$2:B$1000,ISNUMBER(SEARCH(A98,Objectives!D$2:D$1000)),"")))}
C99: SLR-PLN-05 | D99: The NAS shall release a flight only when the dispatcher and the captain both agree that it can be flown safely as planned. (also answers SN-CRW-01, SN-GOV-02) | E99: HLR-CRW-01 | F99: The flight crew shall safely control the flight from origin to destination, as cleared by air traffic control with or without negotiation, and in collaboration with flight operations. (also comes from SLR-EXE-02, SLR-CLR-08) | G99: {=IF(A99="","",_xlfn.TEXTJOIN(", ",TRUE,_xlfn._xlws.FILTER(Objectives!B$2:B$1000,ISNUMBER(SEARCH(A99,Objectives!D$2:D$1000)),"")))}
E100: HLR-OPS-04 | F100: The dispatcher shall release a flight only with the captain's agreement that it can be flown safely as planned. | G100: {=IF(A100="","",_xlfn.TEXTJOIN(", ",TRUE,_xlfn._xlws.FILTER(Objectives!B$2:B$1000,ISNUMBER(SEARCH(A100,Objectives!D$2:D$1000)),"")))}
...

Sheet Coverage
A1: Check | B1: Count | C1: Which
A2: Stakeholder requirements in the study | B2: 11 | C2: SN-AIR-01, SN-AIR-02, SN-AIR-03, SN-AIR-05, SN-ATC-01, SN-ATC-02, SN-ATC-04, SN-CRW-03, SN-CRW-06, SN-CRW-07, SN-CRW-08
A3: Stakeholder requirements tagged background | B3: 2 | C3: SN-GOV-01, SN-ENV-01
A4: Stakeholder requirements out of the study | B4: 17 | C4: SN-AIR-04, SN-AIR-06, SN-ATC-03, SN-ATC-05, SN-CRW-01, SN-CRW-02, SN-CRW-04, SN-CRW-05, SN-GOV-02, SN-ENV-02, SN-APT-01, SN-APT-02, SN-APT-03, SN-PAX-01, SN-PAX-02, SN-PAX-03, SN-MIL-01
A5: System requirements in the study | B5: 23 | C5: SLR-PLN-01, SLR-PLN-02, SLR-PLN-04, SLR-PLN-05, SLR-PLN-06, SLR-PLN-07, SLR-CLR-01, SLR-CLR-02, SLR-CLR-04, SLR-CLR-08, SLR-CLR-09, SLR-CLR-10, SLR-CLR-13, SLR-CLR-15, SLR-INF-01, SLR-INF-02, SLR-INF-07, SLR-EXE-02, SLR-EXE-03, SLR-EXE-06, SLR-APT-04, SLR-MEA-01, SLR-MEA-02
A6: System requirements out of the study | B6: 19 | C6: SLR-PLN-08, SLR-PLN-09, SLR-FLW-04, SLR-FLW-05, SLR-FLW-06, SLR-FLW-07, SLR-CLR-03, SLR-CLR-05, SLR-CLR-14, SLR-INF-05, SLR-INF-06, SLR-EXE-01, SLR-EXE-04, SLR-APT-01, SLR-APT-02, SLR-APT-03, SLR-APT-05, SLR-MEA-03, SLR-MEA-04
A7: Sub-system HLRs | B7: 29 | C7: HLR-CRW-01, HLR-CRW-02, HLR-CRW-03, HLR-CRW-04, HLR-CRW-05, HLR-OPS-01, HLR-OPS-02, HLR-OPS-03, HLR-OPS-04, HLR-OPS-05, HLR-OPS-06, HLR-OPS-07, HLR-ATC-01, HLR-ATC-02, HLR-ATC-03, HLR-ATC-04, HLR-ATC-05, HLR-ATC-06, HLR-ATC-07, HLR-ATC-08, HLR-ATC-09, HLR-ACF-01, HLR-ACF-02, HLR-ACF-03, HLR-ACF-04, HLR-ACF-05, HLR-ACF-06, HLR-APT-01, HLR-APT-02
A8: GAP: stakeholder requirement with no system requirement | B8: 0
A9: GAP: system requirement with no stakeholder parent | B9: 0
A10: GAP: system requirement in the study with no HLR | B10: 0
A11: GAP: system requirement with no allocation | B11: 0
A12: GAP: HLR with no allocation | B12: 0
A13: CHECK: out-of-study system requirement that has an HLR | B13: 0
A14: CHECK: in-study system requirement whose only parents are out of study | B14: 0
A15: CHECK: HLR reached only through out-of-study system requirements | B15: 0

Sheet Objectives
A1: Category | B1: Objective row | C1: Trajectory impact | D1: Stakeholder requirements in the study | E1: Background / out of study | F1: In-study system requirements reached | G1: HLRs reached | H1: Review notes
A2: Airline | B2: Fuel cost | C2: Yes | D2: SN-AIR-01, SN-AIR-05 | F2: SLR-PLN-01, SLR-PLN-02, SLR-CLR-09, SLR-CLR-13, SLR-INF-02, SLR-EXE-03, SLR-MEA-02 | G2: HLR-CRW-03, HLR-CRW-05, HLR-OPS-01, HLR-OPS-05, HLR-OPS-07, HLR-ATC-05, HLR-ATC-07, HLR-ATC-08, HLR-ACF-01, HLR-ACF-05
A3: Airline | B3: Crew cost | C3: Indirect | D3: SN-AIR-01 | F3: SLR-PLN-01, SLR-PLN-02, SLR-CLR-09, SLR-EXE-03, SLR-MEA-02 | G3: HLR-CRW-03, HLR-CRW-05, HLR-OPS-01, HLR-OPS-07, HLR-ATC-07, HLR-ACF-01, HLR-ACF-05
A4: Airline | B4: Aircraft utilization | C4: Indirect | D4: SN-AIR-02 | F4: SLR-INF-07, SLR-APT-04 | G4: HLR-CRW-04, HLR-OPS-06, HLR-APT-01, HLR-APT-02
A5: Airline | B5: Maintenance | C5: Indirect | D5: SN-AIR-01 | F5: SLR-PLN-01, SLR-PLN-02, SLR-CLR-09, SLR-EXE-03, SLR-MEA-02 | G5: HLR-CRW-03, HLR-CRW-05, HLR-OPS-01, HLR-OPS-07, HLR-ATC-07, HLR-ACF-01, HLR-ACF-05
A6: Airline | B6: Schedule integrity | C6: Yes | D6: SN-AIR-02, SN-AIR-03, SN-AIR-05 | F6: SLR-CLR-04, SLR-CLR-13, SLR-INF-02, SLR-INF-07, SLR-APT-04 | G6: HLR-CRW-04, HLR-OPS-05, HLR-OPS-06, HLR-ATC-05, HLR-ATC-08, HLR-ACF-04, HLR-ACF-05, HLR-APT-01, HLR-APT-02
A7: Airline | B7: Passenger connections | C7: Yes | D7: SN-AIR-02, SN-AIR-05 | E7: SN-AIR-04 (out of study) | F7: SLR-CLR-13, SLR-INF-02, SLR-INF-07, SLR-APT-04 | G7: HLR-CRW-04, HLR-OPS-05, HLR-OPS-06, HLR-ATC-05, HLR-ATC-08, HLR-ACF-05, HLR-APT-01, HLR-APT-02
A8: Airline | B8: Delay cost | C8: Yes | D8: SN-AIR-01, SN-AIR-03 | E8: SN-AIR-04 (out of study) | F8: SLR-PLN-01, SLR-PLN-02, SLR-CLR-04, SLR-CLR-09, SLR-INF-07, SLR-EXE-03, SLR-MEA-02 | G8: HLR-CRW-03, HLR-CRW-04, HLR-CRW-05, HLR-OPS-01, HLR-OPS-06, HLR-OPS-07, HLR-ATC-07, HLR-ACF-01, HLR-ACF-04, HLR-ACF-05
A9: Airline | B9: Revenue | C9: Indirect | D9: SN-AIR-01 | F9: SLR-PLN-01, SLR-PLN-02, SLR-CLR-09, SLR-EXE-03, SLR-MEA-02 | G9: HLR-CRW-03, HLR-CRW-05, HLR-OPS-01, HLR-OPS-07, HLR-ATC-07, HLR-ACF-01, HLR-ACF-05
A10: Airline | B10: Dispatch reliability | C10: Indirect | D10: SN-AIR-02 | F10: SLR-INF-07, SLR-APT-04 | G10: HLR-CRW-04, HLR-OPS-06, HLR-APT-01, HLR-APT-02
A11: Airline | B11: Flight Safety | C11: Yes | D11: SN-ATC-01 | E11: SN-PAX-01 (out of study) | F11: SLR-PLN-06, SLR-CLR-01, SLR-CLR-02, SLR-INF-01, SLR-EXE-02 | G11: HLR-CRW-01, HLR-OPS-02, HLR-ATC-01, HLR-ATC-02, HLR-ATC-03, HLR-ATC-04, HLR-ACF-02, HLR-ACF-06
A12: Passenger | B12: Ticket price | C12: No | D12: SN-AIR-01 | F12: SLR-PLN-01, SLR-PLN-02, SLR-CLR-09, SLR-EXE-03, SLR-MEA-02 | G12: HLR-CRW-03, HLR-CRW-05, HLR-OPS-01, HLR-OPS-07, HLR-ATC-07, HLR-ACF-01, HLR-ACF-05
A13: Passenger | B13: Travel time | C13: Yes | D13: SN-AIR-02 | E13: SN-PAX-02 (out of study) | F13: SLR-INF-07, SLR-APT-04 | G13: HLR-CRW-04, HLR-OPS-06, HLR-APT-01, HLR-APT-02
A14: Passenger | B14: Connection reliability | C14: Yes | D14: SN-AIR-02 | E14: SN-PAX-02 (out of study) | F14: SLR-INF-07, SLR-APT-04 | G14: HLR-CRW-04, HLR-OPS-06, HLR-APT-01, HLR-APT-02
A15: Passenger | B15: Schedule convenience | C15: Indirect | D15: SN-AIR-01 | F15: SLR-PLN-01, SLR-PLN-02, SLR-CLR-09, SLR-EXE-03, SLR-MEA-02 | G15: HLR-CRW-03, HLR-CRW-05, HLR-OPS-01, HLR-OPS-07, HLR-ATC-07, HLR-ACF-01, HLR-ACF-05
A16: Passenger | B16: Comfort | C16: Yes | D16: SN-AIR-01 | E16: SN-PAX-03 (out of study) | F16: SLR-PLN-01, SLR-PLN-02, SLR-CLR-09, SLR-EXE-03, SLR-MEA-02 | G16: HLR-CRW-03, HLR-CRW-05, HLR-OPS-01, HLR-OPS-07, HLR-ATC-07, HLR-ACF-01, HLR-ACF-05
A17: Passenger | B17: Disruption risk | C17: Indirect | D17: SN-AIR-02 | E17: SN-PAX-02 (out of study) | F17: SLR-INF-07, SLR-APT-04 | G17: HLR-CRW-04, HLR-OPS-06, HLR-APT-01, HLR-APT-02
A18: ATC / ANSP | B18: Safety/separation | C18: Yes | D18: SN-ATC-01 | F18: SLR-PLN-06, SLR-CLR-01, SLR-CLR-02, SLR-INF-01, SLR-EXE-02 | G18: HLR-CRW-01, HLR-OPS-02, HLR-ATC-01, HLR-ATC-02, HLR-ATC-03, HLR-ATC-04, HLR-ACF-02, HLR-ACF-06
A19: ATC / ANSP | B19: Sector workload | C19: Yes | D19: SN-ATC-04 | F19: SLR-CLR-15 | G19: HLR-ATC-06
A20: ATC / ANSP | B20: Capacity | C20: Yes | D20: SN-ATC-02 | F20: SLR-PLN-06 | G20: HLR-OPS-02
A21: ATC / ANSP | B21: Predictability | C21: Yes | D21: SN-AIR-02 | E21: SN-ATC-03 (out of study) | F21: SLR-INF-07, SLR-APT-04 | G21: HLR-CRW-04, HLR-OPS-06, HLR-APT-01, HLR-APT-02
A22: ATC / ANSP | B22: Delay (ATC-attributed) | C22: Yes | D22: SN-AIR-02 | E22: SN-ATC-05 (out of study) | F22: SLR-INF-07, SLR-APT-04 | G22: HLR-CRW-04, HLR-OPS-06, HLR-APT-01, HLR-APT-02
A23: ATC / ANSP | B23: Traffic complexity | C23: Yes | D23: SN-ATC-04 | F23: SLR-CLR-15 | G23: HLR-ATC-06
A24: Airport | B24: Gate utilization | C24: Indirect | D24: SN-AIR-02 | E24: SN-APT-01 (out of study) | F24: SLR-INF-07, SLR-APT-04 | G24: HLR-CRW-04, HLR-OPS-06, HLR-APT-01, HLR-APT-02
A25: Airport | B25: Runway utilization | C25: Yes | D25: SN-AIR-02 | E25: SN-APT-02 (out of study) | F25: SLR-INF-07, SLR-APT-04 | G25: HLR-CRW-04, HLR-OPS-06, HLR-APT-01, HLR-APT-02
A26: Airport | B26: Surface congestion | C26: Yes | D26: SN-AIR-02 | E26: SN-APT-03 (out of study) | F26: SLR-INF-07, SLR-APT-04 | G26: HLR-CRW-04, HLR-OPS-06, HLR-APT-01, HLR-APT-02
A27: Airport | B27: Turnaround performance | C27: Indirect | D27: SN-AIR-02 | E27: SN-APT-01 (out of study) | F27: SLR-INF-07, SLR-APT-04 | G27: HLR-CRW-04, HLR-OPS-06, HLR-APT-01, HLR-APT-02
A28: Airport | B28: Passenger throughput | C28: No | D28: SN-AIR-02 | E28: SN-APT-01 (out of study) | F28: SLR-INF-07, SLR-APT-04 | G28: HLR-CRW-04, HLR-OPS-06, HLR-APT-01, HLR-APT-02
A29: Flight Crew | B29: Safety | C29: Yes | D29: SN-CRW-03, SN-CRW-06, SN-CRW-07 | E29: SN-CRW-01 (out of study), SN-CRW-02 (out of study) | F29: SLR-PLN-07, SLR-CLR-01, SLR-CLR-02, SLR-CLR-10, SLR-INF-02, SLR-EXE-03, SLR-EXE-06 | G29: HLR-CRW-02, HLR-CRW-03, HLR-CRW-04, HLR-CRW-05, HLR-OPS-03, HLR-OPS-05, HLR-OPS-06, HLR-ATC-01, HLR-ATC-02, HLR-ATC-04, HLR-ATC-08, HLR-ACF-01, HLR-ACF-03, HLR-ACF-05, HLR-ACF-06, HLR-APT-02
A30: Flight Crew | B30: Workload | C30: Yes | D30: SN-CRW-03, SN-CRW-08 | F30: SLR-CLR-04, SLR-CLR-10, SLR-INF-02, SLR-EXE-03, SLR-EXE-06 | G30: HLR-CRW-02, HLR-CRW-03, HLR-CRW-04, HLR-CRW-05, HLR-OPS-05, HLR-OPS-06, HLR-ATC-04, HLR-ATC-08, HLR-ACF-01, HLR-ACF-03, HLR-ACF-04, HLR-ACF-05
A31: Flight Crew | B31: Procedural compliance | C31: Yes | D31: SN-CRW-07, SN-CRW-08 | E31: SN-CRW-02 (out of study) | F31: SLR-PLN-07, SLR-CLR-04 | G31: HLR-CRW-04, HLR-CRW-05, HLR-OPS-03, HLR-OPS-06, HLR-ACF-04, HLR-APT-02
A32: Flight Crew | B32: Schedule/duty constraints | C32: Indirect | D32: SN-AIR-02 | E32: SN-CRW-05 (out of study) | F32: SLR-INF-07, SLR-APT-04 | G32: HLR-CRW-04, HLR-OPS-06, HLR-APT-01, HLR-APT-02
A33: Flight Crew | B33: Operational flexibility | C33: Yes | D33: SN-AIR-01, SN-AIR-05 | E33: SN-CRW-01 (out of study), SN-CRW-04 (out of study) | F33: SLR-PLN-01, SLR-PLN-02, SLR-CLR-09, SLR-CLR-13, SLR-INF-02, SLR-EXE-03, SLR-MEA-02 | G33: HLR-CRW-03, HLR-CRW-05, HLR-OPS-01, HLR-OPS-05, HLR-OPS-07, HLR-ATC-05, HLR-ATC-07, HLR-ATC-08, HLR-ACF-01, HLR-ACF-05
A34: Environmental / Societal | B34: CO2 | C34: Yes | D34: SN-AIR-01, SN-AIR-05 | E34: SN-ENV-01 (background) | F34: SLR-PLN-01, SLR-PLN-02, SLR-CLR-09, SLR-CLR-13, SLR-INF-02, SLR-EXE-03, SLR-MEA-02 | G34: HLR-CRW-03, HLR-CRW-05, HLR-OPS-01, HLR-OPS-05, HLR-OPS-07, HLR-ATC-05, HLR-ATC-07, HLR-ATC-08, HLR-ACF-01, HLR-ACF-05
A35: Environmental / Societal | B35: NOx | C35: Yes | D35: SN-AIR-01, SN-AIR-05 | E35: SN-ENV-01 (background) | F35: SLR-PLN-01, SLR-PLN-02, SLR-CLR-09, SLR-CLR-13, SLR-INF-02, SLR-EXE-03, SLR-MEA-02 | G35: HLR-CRW-03, HLR-CRW-05, HLR-OPS-01, HLR-OPS-05, HLR-OPS-07, HLR-ATC-05, HLR-ATC-07, HLR-ATC-08, HLR-ACF-01, HLR-ACF-05
A36: Environmental / Societal | B36: Contrail/climate effects | C36: Yes | D36: SN-AIR-01, SN-AIR-05 | E36: SN-ENV-01 (background) | F36: SLR-PLN-01, SLR-PLN-02, SLR-CLR-09, SLR-CLR-13, SLR-INF-02, SLR-EXE-03, SLR-MEA-02 | G36: HLR-CRW-03, HLR-CRW-05, HLR-OPS-01, HLR-OPS-05, HLR-OPS-07, HLR-ATC-05, HLR-ATC-07, HLR-ATC-08, HLR-ACF-01, HLR-ACF-05
A37: Environmental / Societal | B37: Noise | C37: Yes | D37: SN-AIR-01, SN-AIR-05 | E37: SN-ENV-02 (out of study) | F37: SLR-PLN-01, SLR-PLN-02, SLR-CLR-09, SLR-CLR-13, SLR-INF-02, SLR-EXE-03, SLR-MEA-02 | G37: HLR-CRW-03, HLR-CRW-05, HLR-OPS-01, HLR-OPS-05, HLR-OPS-07, HLR-ATC-05, HLR-ATC-07, HLR-ATC-08, HLR-ACF-01, HLR-ACF-05
A38: Environmental / Societal | B38: Local air quality | C38: Indirect | D38: SN-AIR-01, SN-AIR-05 | E38: SN-ENV-01 (background) | F38: SLR-PLN-01, SLR-PLN-02, SLR-CLR-09, SLR-CLR-13, SLR-INF-02, SLR-EXE-03, SLR-MEA-02 | G38: HLR-CRW-03, HLR-CRW-05, HLR-OPS-01, HLR-OPS-05, HLR-OPS-07, HLR-ATC-05, HLR-ATC-07, HLR-ATC-08, HLR-ACF-01, HLR-ACF-05
A39: Military | B39: Mission effectiveness | C39: Yes | E39: (no requirement)
A40: Military | B40: Mission timing | C40: Yes | E40: (no requirement)
A41: Military | B41: Fuel availability | C41: Indirect | E41: (no requirement)
A42: Military | B42: Airspace access | C42: Yes | E42: SN-MIL-01 (out of study)
A43: Military | B43: Operational security | C43: No | E43: (no requirement)
A44: Military | B44: Resilience | C44: Indirect | E44: (no requirement)
A45: Airline | B45: (no objective row) | E45: SN-AIR-06 (out of study)
A46: Regulator | B46: (no objective row) | E46: SN-GOV-01 (background)
A47: Regulator | B47: (no objective row) | E47: SN-GOV-02 (out of study)

Sheet Stakeholder reqs
A1: ID | B1: Group | C1: Requirement | D1: Objective rows | E1: Answered by | F1: Scope | G1: Status | H1: Basis | I1: Evidence | J1: Rationale (from the model) | K1: Review notes
A2: SN-AIR-01 | B2: Airline | C2: The NAS shall provide a means for the airline to plan and fly each flight on the route, altitude and speed it chooses. | D2: Airline: Fuel cost; Airline: Delay cost; Airline: Crew cost; Airline: Maintenance; Airline: Revenue; Passenger: Ticket price; Passenger: Schedule convenience; Passenger: Comfort; Flight Crew: Operational flexibility; Environmental / Societal: CO2; Environmental / Societal: NOx; Environmental / Societal: Contrail/climate effects; Environmental / Societal: Noise; Environmental / Societal: Local air quality | E2: SLR-PLN-01, SLR-PLN-02, SLR-CLR-09, SLR-EXE-03, SLR-MEA-02 | F2: inStudy | G2: draft | H2: [B] | I2: mori2022massCruise; munro2018managingVariability | J2: In the study: the planned cruise altitude and speed are what a conflict resolution takes the aircraft away from, so this is what the experiment scores a resolution against. The owner struck 'at its lowest operating cost' (hand review 2026-10-11): what the airline optimizes for is the airline's own business. The owner struck ', so that the flight is flown within safety and capacity limits' (hand review 2026-10-20). Objective rows added by the owner in the workbook review of 2026-10-22 (D-032): Airline: Crew cost; Airline: Maintenance; Airline: Revenue; Passenger: Ticket price; Passenger: Schedule convenience; Passenger: Comfort; Flight Crew: Operational flexibility; Environmental / Societal: CO2; Environmental / Societal: NOx; Environmental / Societal: Contrail/climate effects; Environmental / Societal: Noise; Environmental / Societal: Local air quality. Owner on 'Passenger: Ticket price' (2026-10-22): the airline sets prices from its costs, as represented in the fuel, time and maintenance impacts of its flight schedules as planned.
A3: SN-AIR-02 | B3: Airline | C3: The NAS shall provide a means for each flight to achieve arrival at its destination gate at its scheduled arrival time. | D3: Airline: Schedule integrity; Airline: Aircraft utilization; Airline: Passenger connections; Airline: Dispatch reliability; Passenger: Travel time; Passenger: Connection reliability; Passenger: Disruption risk; ATC / ANSP: Predictability; ATC / ANSP: Delay (ATC-attributed); Airport: Gate utilization; Airport: Runway utilization; Airport: Surface congestion; Airport: Turnaround performance; Airport: Passenger throughput; Flight Crew: Schedule/duty constraints | E3: SLR-INF-07, SLR-APT-01, SLR-APT-04, SLR-MEA-03 | F3: inStudy | G3: draft | H3: [C] | J3: In the study: the time side of the fuel-against-time trade, and the reason one flight's connections can outweigh its fuel (case D of the experiment). Owner's wording, hand review 2026-10-10. Objective rows added by the owner in the workbook review of 2026-10-22 (D-032): Airline: Dispatch reliability; Passenger: Travel time; Passenger: Connection reliability; Passenger: Disruption risk; ATC / ANSP: Predictability; ATC / ANSP: Delay (ATC-attributed); Airport: Gate utilization; Airport: Runway utilization; Airport: Surface congestion; Airport: Turnaround performance; Airport: Passenger throughput; Flight Crew: Schedule/duty constraints.
A4: SN-AIR-03 | B4: Airline | C4: The NAS shall inform the airline of airspace and airport constraints that will delay or reroute its flights early enough for the airline to re-plan. | D4: Airline: Delay cost; Airline: Schedule integrity | E4: SLR-FLW-07, SLR-CLR-04, SLR-INF-07 | F4: inStudy | G4: draft | H4: [A] | I4: faa2025jo72103ee | J4: In the study: flights are separated as filed; as uncertainty is realized, aircraft deviate and interventions are needed (owner, hand review 2026-10-11). The intervention is the constraint the airline needs to hear about, and the crew and the dispatchers are the ones who coordinate to make that happen (owner, 2026-10-11). Traffic management initiatives are outside the study (D-021).
A5: SN-AIR-04 | B5: Airline | C5: The NAS shall let the airline choose which of its own flights takes a delay that the airline has been assigned. | D5: Airline: Delay cost; Airline: Passenger connections | E5: SLR-FLW-04 | F5: outOfStudy | G5: draft | H5: [A] | I5: faa2025jo72103ee | J5: Restored as out of study (D-031): the owner's hand review of 2026-10-20 keeps every stakeholder requirement of the first draft and makes the cut at the sub-system (HLR) tier. Text as on the 2026-10-10 print. Struck 2026-10-10: 'This is about slot swapping... seems like it's only on strategic timelines, not tactical like I'm studying.' JO 7210.3EE 18-10-12 places it inside a ground delay program, before departure.
A6: SN-AIR-05 | B6: Airline | C6: The NAS shall take the airline's priorities for a flight (fuel against time, and protected connections) into account when a change to that flight's trajectory is required. | D6: Airline: Fuel cost; Airline: Schedule integrity; Airline: Passenger connections; Flight Crew: Operational flexibility; Environmental / Societal: CO2; Environmental / Societal: NOx; Environmental / Societal: Contrail/climate effects; Environmental / Societal: Noise; Environmental / Societal: Local air quality | E6: SLR-CLR-13, SLR-INF-02 | F6: inStudy | G6: draft | H6: [B] | I6: schultz2012adaptiveClimb; coppenbarger1999climbPrediction; kulkarni2019ctopSlotSubstitution | J6: In the study: this is the requirement the experiment is about (knowledge/models/experiment-definition.md section 2). Met today in part, before departure (owner, 2026-10-22): in the FAA's Collaborative Trajectory Options Program the airline submits a Trajectory Options Set, each route option carrying a Relative Trajectory Cost in equivalent ground-delay minutes, and the FAA's algorithm adds that cost to the assigned delay and picks the cheapest option (kulkarni2019ctopSlotSubstitution, p. 4). It is not met in tactical conflict resolution in cruise, the decision the study examines: the controller does not receive weight or cost index. Owner's wording, hand review 2026-10-10. Objective rows added by the owner in the workbook review of 2026-10-22 (D-032): Flight Crew: Operational flexibility; Environmental / Societal: CO2; Environmental / Societal: NOx; Environmental / Societal: Contrail/climate effects; Environmental / Societal: Noise; Environmental / Societal: Local air quality.
A7: SN-AIR-06 | B7: Airline | C7: The NAS shall keep the airline's commercially sensitive flight data (aircraft weight, cost index, connection priorities) private. | D7: none | E7: SLR-INF-05 | F7: outOfStudy | G7: draft | H7: [B] | I7: schultz2012adaptiveClimb | J7: Restored as out of study (D-031): the owner's hand review of 2026-10-20 keeps every stakeholder requirement of the first draft and makes the cut at the sub-system (HLR) tier. Text as on the 2026-10-10 print. Struck 2026-10-10: 'Important & real, but not pertinent to my project per D-007!' Carried as an assumption (D-020 item 4). No objective row matches it.
A8: SN-ATC-01 | B8: Air traffic control | C8: The NAS shall keep every controlled aircraft separated from every other aircraft by at least the applicable separation minimum. | D8: ATC / ANSP: Safety/separation; Airline: Flight Safety | E8: SLR-PLN-06, SLR-CLR-01, SLR-CLR-02, SLR-CLR-03, SLR-CLR-05, SLR-INF-01, SLR-EXE-02 | F8: inStudy | G8: draft | H8: [A] | I8: faa2025jo711065bb | J8: In the study: the hard constraint every resolution option must meet. It is never traded against cost (knowledge/models/experiment-definition.md section 6). Objective rows added by the owner in the workbook review of 2026-10-22 (D-032): Airline: Flight Safety.
A9: SN-ATC-02 | B9: Air traffic control | C9: The NAS shall keep the number of aircraft in each sector and at each airport within its declared capacity. | D9: ATC / ANSP: Capacity | E9: SLR-PLN-06, SLR-PLN-08, SLR-FLW-06, SLR-APT-02 | F9: inStudy | G9: draft | H9: [A] | I9: faa2025jo72103ee | J9: In the study: context. It is the capacity limit named in SN-AIR-01. Not marked in either hand review. The workload rows moved back to SN-ATC-04 (D-021).
A10: SN-ATC-03 | B10: Air traffic control | C10: The NAS shall make the path each controlled aircraft will fly known to its controller in advance. | D10: ATC / ANSP: Predictability | E10: SLR-PLN-06, SLR-FLW-06, SLR-CLR-03, SLR-INF-01, SLR-EXE-01, SLR-EXE-02 | F10: outOfStudy | G10: draft | H10: [B] | I10: coppenbarger1999climbPrediction | J10: Restored as out of study (D-031): the owner's hand review of 2026-10-20 keeps every stakeholder requirement of the first draft and makes the cut at the sub-system (HLR) tier. Text as on the 2026-10-10 print. Struck 2026-10-10: 'Not D-007'.
A11: SN-ATC-04 | B11: Air traffic control | C11: The NAS shall keep the number of control actions a sector controller must take within what one sector team can sustain. | D11: ATC / ANSP: Sector workload; ATC / ANSP: Traffic complexity | E11: SLR-CLR-15 | F11: inStudy | G11: draft | H11: [B] | I11: rantanen2012conflictManeuvers; kirwan2001coraStrategies | J11: Struck in the first hand review and brought back in the second (owner, 2026-10-11: 'Let's bring back SN-ATC-04'). In the study: instruction count is one of the experiment's two scored columns. Workload is a ceiling, not something to minimize: a controller who is not overworked can give as many instructions as wanted (owner, same review).
A12: SN-ATC-05 | B12: Air traffic control | C12: The NAS shall share unavoidable delay equitably among airspace users. | D12: ATC / ANSP: Delay (ATC-attributed) | E12: SLR-FLW-05, SLR-MEA-04 | F12: outOfStudy | G12: draft | H12: [A] | I12: faa2025jo72103ee | J12: Restored as out of study (D-031): the owner's hand review of 2026-10-20 keeps every stakeholder requirement of the first draft and makes the cut at the sub-system (HLR) tier. Text as on the 2026-10-10 print. Struck 2026-10-10 with no mark: its only system requirements were about traffic management initiatives.
A13: SN-CRW-01 | B13: Flight crew | C13: The NAS shall preserve the captain's final authority over the safe conduct of the flight. | D13: Flight Crew: Safety; Flight Crew: Operational flexibility | E13: SLR-PLN-05, SLR-CLR-08, SLR-EXE-04 | F13: outOfStudy | G13: draft | H13: [A] | I13: 14 CFR 91.3 | J13: Restored as out of study (D-031): the owner's hand review of 2026-10-20 keeps every stakeholder requirement of the first draft and makes the cut at the sub-system (HLR) tier. Text as on the 2026-10-10 print. Struck 2026-10-10 (crossed out).
A14: SN-CRW-02 | B14: Flight crew | C14: The NAS shall give the flight crew the information needed for each phase of flight before that phase begins. | D14: Flight Crew: Safety; Flight Crew: Procedural compliance | E14: SLR-PLN-01, SLR-PLN-07, SLR-INF-06, SLR-EXE-06 | F14: outOfStudy | G14: draft | H14: [B] | I14: seamster2011collabSystems | J14: Restored as out of study (D-031): the owner's hand review of 2026-10-20 keeps every stakeholder requirement of the first draft and makes the cut at the sub-system (HLR) tier. Text as on the 2026-10-10 print. Struck 2026-10-10 and replaced by the owner's SN-CRW-07.
A15: SN-CRW-03 | B15: Flight crew | C15: The NAS shall give the flight crew only trajectory clearances and instructions that the aircraft can fly, with enough time to set them up. | D15: Flight Crew: Workload; Flight Crew: Safety | E15: SLR-CLR-10, SLR-INF-02, SLR-EXE-03, SLR-EXE-06 | F15: inStudy | G15: draft | H15: [SME] | J15: In the study: a climb the aircraft is too heavy to make is the clearance the baseline can issue and the improved architecture avoids. The only flight crew requirement of the first draft the owner kept. 'Clearances and' added by the owner (hand review 2026-10-20).
A16: SN-CRW-04 | B16: Flight crew | C16: The NAS shall let the flight crew ask for a trajectory change and get an answer. | D16: Flight Crew: Operational flexibility | E16: SLR-CLR-09 | F16: outOfStudy | G16: draft | H16: [B] | I16: engility2014tasarAlaska | J16: Restored as out of study (D-031): the owner's hand review of 2026-10-20 keeps every stakeholder requirement of the first draft and makes the cut at the sub-system (HLR) tier. Text as on the 2026-10-10 print. Struck 2026-10-10 (crossed out).
A17: SN-CRW-05 | B17: Flight crew | C17: The NAS shall keep each flight crew member within flight and duty time limits. | D17: Flight Crew: Schedule/duty constraints | E17: SLR-PLN-09 | F17: outOfStudy | G17: draft | H17: [C] | I17: 14 CFR Part 117 | J17: Restored as out of study (D-031): the owner's hand review of 2026-10-20 keeps every stakeholder requirement of the first draft and makes the cut at the sub-system (HLR) tier. Text as on the 2026-10-10 print. Struck 2026-10-10: 'Not D-007'.
A18: SN-CRW-06 | B18: Flight crew | C18: The NAS shall provide the flight crew clearances that account for air traffic. | D18: Flight Crew: Safety | E18: SLR-CLR-01, SLR-CLR-02 | F18: inStudy | G18: draft | H18: [SME] | J18: Written by the owner in the hand review of 2026-10-10 (flight crew note 1). In the study: the clearance that resolves the conflict is the thing the crew receives. Objective row confirmed by the owner (hand review 2026-10-11).
A19: SN-CRW-07 | B19: Flight crew | C19: The NAS shall inform the flight crew of weather, traffic and other safety considerations. | D19: Flight Crew: Safety; Flight Crew: Procedural compliance | E19: SLR-PLN-07 | F19: inStudy | G19: draft | H19: [SME] | J19: Written by the owner in the hand review of 2026-10-10 (flight crew note 2). In the study: what the crew knows when it accepts, refuses or asks to change a clearance. On 2026-10-11 the owner replaced 'traffic management initiatives' with 'other safety considerations', as a catch-all. Objective rows confirmed by the owner (hand review 2026-10-11).
A20: SN-CRW-08 | B20: Flight crew | C20: The NAS shall facilitate control of the aircraft across regional sectors, coordinating controls, clearances and handoffs. | D20: Flight Crew: Workload; Flight Crew: Procedural compliance | E20: SLR-CLR-04 | F20: inStudy | G20: draft | H20: [SME] | J20: Written by the owner in the hand review of 2026-10-10 (flight crew note 3). In the study: the conflict is resolved by one sector controller, whose authority ends at the sector boundary. Objective rows confirmed by the owner (hand review 2026-10-11).
A21: SN-GOV-01 | B21: Regulator | C21: The NAS shall conduct every flight within the operating rules of 14 CFR and the FAA's air traffic orders. | D21: none | E21: SLR-PLN-04, SLR-PLN-05, SLR-PLN-09, SLR-CLR-08, SLR-EXE-06, SLR-MEA-01 | F21: background | G21: draft | H21: [A] | I21: faa2025jo711065bb; faa2025jo72103ee; 14 CFR 91; 14 CFR 121 | J21: In the study: the rules are held fixed (D-007), so both the baseline and the improved architecture must stay inside them. Governance has no table in knowledge/models/stakeholder-objective-ontology.md; the objective is 'Regulatory Compliance' in the enterprise objective hierarchy in knowledge/models/stakeholder-register.md. The owner judged adding a Governance table not important (hand review 2026-10-10). Owner (hand review 2026-10-20): 'How is this relevant via D-007? I think I need to remove.' Kept and tagged background (D-031): the regulator is a boundary actor whose rules are an input to the study, not a stakeholder whose objectives it weighs.
A22: SN-GOV-02 | B22: Regulator | C22: The NAS shall make one identified authority accountable for each decision that changes a flight's trajectory. | D22: none | E22: SLR-PLN-05, SLR-CLR-05, SLR-EXE-04, SLR-MEA-01 | F22: outOfStudy | G22: draft | H22: [A] | I22: 14 CFR 91.3; 14 CFR 121.533; faa2025jo711065bb | J22: Restored as out of study (D-031): the owner's hand review of 2026-10-20 keeps every stakeholder requirement of the first draft and makes the cut at the sub-system (HLR) tier. Text as on the 2026-10-10 print. Struck 2026-10-10: 'IDK about this one... the Note is an exception!' (the joint dispatcher and captain release). No objective row; from 'Regulatory Compliance' and 'Safety' in the enterprise objective hierarchy.
A23: SN-ENV-01 | B23: Communities and environment | C23: The NAS shall keep the CO2 emitted by each flight as low as safety, economics and capacity allow. | D23: Environmental / Societal: CO2; Environmental / Societal: NOx; Environmental / Societal: Contrail/climate effects; Environmental / Societal: Local air quality | E23: SLR-CLR-13, SLR-APT-03, SLR-MEA-02 | F23: background | G23: draft | H23: [C] | I23: icao2024icecMethodology | J23: In the study: CO2 is fuel burned times 3.16 (D-015), so the experiment's fuel column is also this stakeholder's column. 'Economics' was added by the owner (hand review 2026-10-10) and left standing in the second review. Owner (hand review 2026-10-20): 'This is currently in my cost, but not in my stakeholders. They're treated as background/input.' Tagged background (D-031). Objective rows added by the owner in the workbook review of 2026-10-22 (D-032): Environmental / Societal: NOx; Environmental / Societal: Contrail/climate effects; Environmental / Societal: Local air quality.
A24: SN-ENV-02 | B24: Communities and environment | C24: The NAS shall keep aircraft noise over communities near airports within the published noise abatement procedures. | D24: Environmental / Societal: Noise | E24: SLR-APT-05 | F24: outOfStudy | G24: draft | H24: [C] | J24: Restored as out of study (D-031): the owner's hand review of 2026-10-20 keeps every stakeholder requirement of the first draft and makes the cut at the sub-system (HLR) tier. Text as on the 2026-10-10 print. Struck 2026-10-10: 'Not important for cruise.'
A25: SN-APT-01 | B25: Airport operator | C25: The NAS shall give the airport operator arrival and departure times reliable enough to assign gates and ground crews. | D25: Airport: Gate utilization; Airport: Turnaround performance; Airport: Passenger throughput | E25: SLR-INF-07, SLR-APT-01 | F25: outOfStudy | G25: draft | H25: [C] | J25: Restored as out of study (D-031): the owner's hand review of 2026-10-20 keeps every stakeholder requirement of the first draft and makes the cut at the sub-system (HLR) tier. Text as on the 2026-10-10 print. Struck 2026-10-10: 'All of these are not D-007'. Objective rows added by the owner in the workbook review of 2026-10-22 (D-032): Airport: Passenger throughput.
A26: SN-APT-02 | B26: Airport operator | C26: The NAS shall use the runway capacity the airport has declared available. | D26: Airport: Runway utilization | E26: SLR-APT-02 | F26: outOfStudy | G26: draft | H26: [C] | J26: Restored as out of study (D-031): the owner's hand review of 2026-10-20 keeps every stakeholder requirement of the first draft and makes the cut at the sub-system (HLR) tier. Text as on the 2026-10-10 print. Struck 2026-10-10: 'All of these are not D-007'.
A27: SN-APT-03 | B27: Airport operator | C27: The NAS shall keep the time aircraft wait on taxiways with engines running as short as practical. | D27: Airport: Surface congestion | E27: SLR-APT-03 | F27: outOfStudy | G27: draft | H27: [C] | J27: Restored as out of study (D-031): the owner's hand review of 2026-10-20 keeps every stakeholder requirement of the first draft and makes the cut at the sub-system (HLR) tier. Text as on the 2026-10-10 print. Struck 2026-10-10: 'All of these are not D-007'.
A28: SN-PAX-01 | B28: Passengers | C28: The NAS shall carry passengers without injury. | D28: Airline: Flight Safety | E28: SLR-PLN-04, SLR-CLR-01, SLR-CLR-08, SLR-EXE-06 | F28: outOfStudy | G28: draft | H28: [C] | J28: Restored as out of study (D-031): the owner's hand review of 2026-10-20 keeps every stakeholder requirement of the first draft and makes the cut at the sub-system (HLR) tier. Text as on the 2026-10-10 print. Struck 2026-10-10: 'Not D-007'. The Passenger table in stakeholder-objective-ontology.md has no safety row; the interest comes from stakeholder-register.md (Social: Passengers, safety and convenience).
A29: SN-PAX-02 | B29: Passengers | C29: The NAS shall get passengers to their destination, including connections, at the time they were sold. | D29: Passenger: Travel time; Passenger: Connection reliability; Passenger: Disruption risk | E29: SLR-MEA-03 | F29: outOfStudy | G29: draft | H29: [C] | J29: Restored as out of study (D-031): the owner's hand review of 2026-10-20 keeps every stakeholder requirement of the first draft and makes the cut at the sub-system (HLR) tier. Text as on the 2026-10-10 print. Struck 2026-10-10: 'Not D-007'.
A30: SN-PAX-03 | B30: Passengers | C30: The NAS shall avoid known turbulence where a route or altitude change allows it. | D30: Passenger: Comfort | E30: SLR-CLR-09, SLR-INF-06 | F30: outOfStudy | G30: draft | H30: [C] | J30: Restored as out of study (D-031): the owner's hand review of 2026-10-20 keeps every stakeholder requirement of the first draft and makes the cut at the sub-system (HLR) tier. Text as on the 2026-10-10 print. Struck 2026-10-10: 'Not D-007'.
A31: SN-MIL-01 | B31: Military airspace users | C31: The NAS shall give military operations sole use of special use airspace while it is scheduled active. | D31: Military: Airspace access | E31: SLR-PLN-08, SLR-FLW-07, SLR-CLR-14 | F31: outOfStudy | G31: draft | H31: [C] | J31: Restored as out of study (D-031): the owner's hand review of 2026-10-20 keeps every stakeholder requirement of the first draft and makes the cut at the sub-system (HLR) tier. Text as on the 2026-10-10 print. Struck 2026-10-10 (crossed out). D-007 makes military operations a boundary actor.

Sheet System reqs
A1: ID | B1: Area | C1: Requirement | D1: Kind | E1: State | F1: Traces to | G1: Allocated to (accountable first) | H1: HLRs under it | I1: Check | J1: Measure | K1: Scope | L1: Status | M1: Basis | N1: Evidence | O1: Rationale (from the model) | P1: Review notes
A2: SLR-PLN-01 | B2: Flight planning and release | C2: The NAS shall produce for each scheduled flight a flight plan that states its route, cruise altitude, cruise speed and fuel load. | D2: Functional | E2: baseline | F2: SN-AIR-01, SN-CRW-02 | G2: Dispatcher | H2: HLR-OPS-01 | I2: Inspection | K2: inStudy | L2: draft | M2: [B] | N2: berry2011aocActors | O2: In the study: the flight plan sets the cruise altitude, speed and fuel load each aircraft has when the conflict occurs.
A3: SLR-PLN-02 | B3: Flight planning and release | C3: The NAS shall compute each flight plan from the performance of the aircraft assigned to the flight. | D3: Functional | E3: baseline | F3: SN-AIR-01 | G3: AOC decision support; Load planner | H3: HLR-OPS-01 | I3: Analysis | K3: inStudy | L3: draft | M3: [B] | N3: mori2022massCruise | O3: The owner struck 'the planned take-off weight' (hand review 2026-10-10). In the study: the cost-optimal altitude depends on mass (mori2022massCruise, Figure 1), which is why two aircraft of one type can want different levels. Owner (hand review 2026-10-11): the next tier can hold several requirements under this one, one per customer or way of computing it: low fidelity, high fidelity, and rules of thumb per aircraft type.
A4: SLR-PLN-04 | B4: Flight planning and release | C4: The NAS shall load each flight with fuel to reach its destination, then its most distant alternate, then fly 45 minutes at normal cruise. | D4: Constraint | E4: baseline | F4: SN-GOV-01, SN-PAX-01 | G4: Dispatcher | H4: HLR-OPS-01 | I4: Inspection | J4: fuel remaining after destination and alternate (minutes at normal cruise). Value: 45 | K4: inStudy | L4: draft | M4: [C] | N4: 14 CFR 121.639 | O4: The owner asked whether this is relevant for the weight assumptions. It is: the fuel load is part of the take-off weight, and the reserve sets the least fuel, and so the least weight, an aircraft can have in cruise. Owner (hand review 2026-10-11): it goes into the low-fidelity model's assumptions. Number and paragraph are from general knowledge; confirm against 14 CFR 121.639 before baselining.
A5: SLR-PLN-05 | B5: Flight planning and release | C5: The NAS shall release a flight only when the dispatcher and the captain both agree that it can be flown safely as planned. | D5: Functional | E5: baseline | F5: SN-GOV-01, SN-CRW-01, SN-GOV-02 | G5: Dispatcher; Flight deck crew | H5: HLR-CRW-01, HLR-OPS-04 | I5: Inspection | K5: inStudy | L5: draft | M5: [A] | N5: 14 CFR 121.533 | O5: Kept by the owner (hand review 2026-10-11). In the study: it is why a controller will issue a descent as a tactical change without negotiation and will not issue a climb. There is no question that a descent can be achieved. A climb is different: the released plan vouches for the planned level and nothing above it. That is the reasoning behind the rule of thumb (owner, 2026-10-11; 'DES' in the hand note is descent).
A6: SLR-PLN-06 | B6: Flight planning and release | C6: The NAS shall file each flight plan with air traffic control before the flight departs. | D6: Interface | E6: baseline | F6: SN-ATC-01, SN-ATC-02, SN-ATC-03 | G6: Dispatcher; Air traffic control | H6: HLR-OPS-02 | I6: Inspection | K6: inStudy | L6: draft | M6: [A] | N6: faa2025aim; faa2025jo72103ee | O6: In the study: the filed plan is the only statement of the airline's intent the controller has today, so it is the baseline that the proposed data share adds to. No lead time is set; the summary of faa2025aim records a 45 to 46 minute point before departure after which a filed plan is locked.
A7: SLR-PLN-07 | B7: Flight planning and release | C7: The NAS shall deliver the dispatch release, flight plan, weather, notices to airmen (NOTAMs) and load sheet to the flight crew before departure. | D7: Interface | E7: baseline | F7: SN-CRW-07, SN-CRW-02 | G7: Dispatcher; Load planner | H7: HLR-CRW-05, HLR-OPS-03, HLR-APT-02 | I7: Inspection | K7: inStudy | L7: draft | M7: [B] | N7: seamster2011collabSystems | O7: In the study: the load sheet is how the actual weight reaches the crew and the flight management system.
A8: SLR-PLN-08 | B8: Flight planning and release | C8: The NAS shall plan each flight to comply with the traffic management initiatives and special use airspace activations published for its time of flight. | D8: Constraint | E8: baseline | F8: SN-ATC-02, SN-MIL-01 | G8: Dispatcher; AOC ATC coordinator | I8: Inspection | K8: outOfStudy | L8: draft | M8: [A] | N8: faa2025jo72103ee | O8: Restored as out of study (D-031): the owner's hand review of 2026-10-20 keeps every stakeholder requirement of the first draft and makes the cut at the sub-system (HLR) tier. Text as on the 2026-10-10 print. Struck 2026-10-11 (crossed out): traffic management initiatives are not tactical interventions. It has no HLR: the study does not depend on it.
A9: SLR-PLN-09 | B9: Flight planning and release | C9: The NAS shall assign to each flight a crew whose duty period, including forecast delay, stays within the limits of 14 CFR Part 117. | D9: Constraint | E9: baseline | F9: SN-CRW-05, SN-GOV-01 | G9: Crew scheduler | I9: Inspection | K9: outOfStudy | L9: draft | M9: [C] | N9: 14 CFR Part 117 | O9: Restored as out of study (D-031): the owner's hand review of 2026-10-20 keeps every stakeholder requirement of the first draft and makes the cut at the sub-system (HLR) tier. Text as on the 2026-10-10 print. Struck 2026-10-10: 'Not important to project.' It has no HLR: the study does not depend on it.
A10: SLR-FLW-04 | B10: Traffic flow management | C10: The NAS shall let an airline exchange its own flights among the departure slots it has been assigned. | D10: Functional | E10: baseline | F10: SN-AIR-04 | G10: Command Center (ATCSCC); AOC ATC coordinator | I10: Demonstration | K10: outOfStudy | L10: draft | M10: [A] | N10: faa2025jo72103ee | O10: Restored as out of study (D-031): the owner's hand review of 2026-10-20 keeps every stakeholder requirement of the first draft and makes the cut at the sub-system (HLR) tier. Text as on the 2026-10-10 print. Struck 2026-10-10 with the whole traffic flow management section: 'TMIs aren't what I'm studying.' It has no HLR: the study does not depend on it.
A11: SLR-FLW-05 | B11: Traffic flow management | C11: The NAS shall assign the delay created by a traffic management initiative equitably among all airspace users. | D11: Performance | E11: baseline | F11: SN-ATC-05 | G11: Command Center (ATCSCC) | I11: Analysis | J11: assigned delay per flight, compared across airlines (minutes) | K11: outOfStudy | L11: draft | M11: [A] | N11: faa2025jo72103ee | O11: Restored as out of study (D-031): the owner's hand review of 2026-10-20 keeps every stakeholder requirement of the first draft and makes the cut at the sub-system (HLR) tier. Text as on the 2026-10-10 print. Struck 2026-10-10 with the whole traffic flow management section: 'TMIs aren't what I'm studying.' It has no HLR: the study does not depend on it.
A12: SLR-FLW-06 | B12: Traffic flow management | C12: The NAS shall release each flight that has an expect departure clearance time (EDCT) within the permitted window around that time. | D12: Performance | E12: baseline | F12: SN-ATC-02, SN-ATC-03 | G12: Control tower; Flight deck crew | I12: Analysis | J12: actual departure time minus EDCT (minutes) | K12: outOfStudy | L12: draft | M12: [C] | N12: faa2025jo72103ee | O12: Restored as out of study (D-031): the owner's hand review of 2026-10-20 keeps every stakeholder requirement of the first draft and makes the cut at the sub-system (HLR) tier. Text as on the 2026-10-10 print. Struck 2026-10-10 (crossed out). It has no HLR: the study does not depend on it.
A13: SLR-FLW-07 | B13: Traffic flow management | C13: The NAS shall give traffic flow managers and airlines the activation schedule of special use airspace before the affected flight plans are filed. | D13: Interface | E13: baseline | F13: SN-MIL-01, SN-AIR-03 | G13: Command Center (ATCSCC) | I13: Inspection | K13: outOfStudy | L13: draft | M13: [C] | O13: Restored as out of study (D-031): the owner's hand review of 2026-10-20 keeps every stakeholder requirement of the first draft and makes the cut at the sub-system (HLR) tier. Text as on the 2026-10-10 print. Struck 2026-10-10 (crossed out). It has no HLR: the study does not depend on it.
A14: SLR-CLR-01 | B14: Clearance, separation and tactical trajectory change | C14: The NAS shall keep each pair of controlled aircraft separated by at least the minimum that JO 7110.65BB sets for the airspace they are in. | D14: Performance | E14: baseline | F14: SN-ATC-01, SN-CRW-06, SN-PAX-01 | G14: Air traffic control; En-route center (ARTCC); Terminal approach control (TRACON) | H14: HLR-ATC-01, HLR-ATC-04, HLR-ACF-06 | I14: Analysis | J14: lateral and vertical distance between each pair of aircraft (NM and ft) | K14: inStudy | L14: draft | M14: [A] | N14: faa2025jo711065bb | O14: In the study: the hard constraint every resolution option must meet; it is not traded (knowledge/models/experiment-definition.md section 6). For en-route radar the minimum is commonly 5 NM or 1,000 ft; those numbers are from general knowledge and are left out of the threshold until the paragraph is confirmed.
A15: SLR-CLR-02 | B15: Clearance, separation and tactical trajectory change | C15: The NAS shall predict a loss of separation between controlled aircraft before it occurs. | D15: Functional | E15: baseline | F15: SN-ATC-01, SN-CRW-06 | G15: ATC decision support | H15: HLR-ATC-02, HLR-ACF-06 | I15: Analysis | K15: inStudy | L15: draft | M15: [B] | N15: engility2014tasarAlaska | O15: In the study: the conflict has to be predicted before any option can be chosen. No look-ahead time is set; engility2014tasarAlaska page 9 uses an eight-minute probe in its own model, which is a candidate.
A16: SLR-CLR-03 | B16: Clearance, separation and tactical trajectory change | C16: The NAS shall give the controlling facility the position, altitude and identity of each controlled aircraft. | D16: Interface | E16: baseline | F16: SN-ATC-01, SN-ATC-03 | G16: Aircraft surveillance system; Air traffic control | I16: Inspection | K16: outOfStudy | L16: draft | M16: [SME] | O16: Restored as out of study (D-031): the owner's hand review of 2026-10-20 keeps every stakeholder requirement of the first draft and makes the cut at the sub-system (HLR) tier. Text as on the 2026-10-10 print. Struck 2026-10-10: 'of course. Not relevant to project.' It has no HLR: the study does not depend on it.
A17: SLR-CLR-04 | B17: Clearance, separation and tactical trajectory change | C17: The NAS shall provide a two-way communication path from the flight crew to the controlling facility and to the dispatcher for the whole flight. | D17: Interface | E17: baseline | F17: SN-CRW-08, SN-AIR-03 | G17: Aircraft communication system; Air traffic control; Dispatcher | H17: HLR-CRW-04, HLR-OPS-06, HLR-ACF-04 | I17: Inspection | K17: inStudy | L17: draft | M17: [SME] | O17: 'Dispatcher too' was added by the owner (hand review 2026-10-10). In the study: the clearance, the crew's 'unable' and any crew request cross this path. It was a derived requirement in the first draft; it now answers SN-CRW-08. 'Of controlled' was struck by the owner (hand review 2026-10-11). It also answers SN-AIR-03: the crew and the dispatchers are the ones who coordinate so that the airline is informed (owner, 2026-10-11).
A18: SLR-CLR-05 | B18: Clearance, separation and tactical trajectory change | C18: The NAS shall change a controlled aircraft's cleared route, altitude or speed only by a clearance from the facility that has control of that aircraft. | D18: Functional | E18: baseline | F18: SN-GOV-02, SN-ATC-01 | G18: Air traffic control | I18: Inspection | K18: outOfStudy | L18: draft | M18: [A] | N18: faa2025jo711065bb | O18: Restored as out of study (D-031): the owner's hand review of 2026-10-20 keeps every stakeholder requirement of the first draft and makes the cut at the sub-system (HLR) tier. Text as on the 2026-10-10 print. Struck 2026-10-10: 'Not relevant to project.' It has no HLR: the study does not depend on it.
A19: SLR-CLR-08 | B19: Clearance, separation and tactical trajectory change | C19: The NAS shall allow the captain to deviate from a clearance when safety requires it, with air traffic control told as soon as practical. | D19: Functional | E19: baseline | F19: SN-GOV-01, SN-CRW-01, SN-PAX-01 | G19: Flight deck crew | H19: HLR-CRW-01 | I19: Inspection | K19: inStudy | L19: draft | M19: [A] | N19: 14 CFR 91.3 | O19: 14 CFR 91.3. In the study: the owner asks whether leaving the choice to the crew, with a response delay, should be one of the experiment's options. Open.
A20: SLR-CLR-09 | B20: Clearance, separation and tactical trajectory change | C20: The NAS shall answer each flight crew request for a route, altitude or speed change with an approval, an amended clearance or a refusal. | D20: Functional | E20: baseline | F20: SN-AIR-01, SN-CRW-04, SN-PAX-03 | G20: Air traffic control; Flight deck crew | H20: HLR-CRW-03, HLR-ATC-07 | I20: Demonstration | K20: inStudy | L20: draft | M20: [B] | N20: engility2014tasarAlaska | O20: The owner asked what its relevance is. In the study: a crew request is the only way today that what the aircraft knows about its own weight and best altitude reaches the controller, so it is the baseline counterpart of the proposed data share. Left standing in the second review.
A21: SLR-CLR-10 | B21: Clearance, separation and tactical trajectory change | C21: The NAS shall issue only clearances that the aircraft can fly. | D21: Constraint | E21: improved | F21: SN-CRW-03 | G21: Air traffic control | H21: HLR-CRW-02, HLR-ATC-04 | I21: Analysis | K21: inStudy | L21: draft | M21: [B] | N21: coppenbarger1999climbPrediction; engility2014tasarAlaska | O21: The owner struck 'at its current weight': weight is not required, but it helps when it is included in the model behind a decision aid. Not fully met today: the ground system assumes one nominal weight per aircraft type (coppenbarger1999climbPrediction), and the crew answers 'unable' when a clearance cannot be flown. The rule in D-013 (offer a climb only at or below FL350) stands in for the missing knowledge. Kept as improved (D-018); left standing in the second review.
A22: SLR-CLR-13 | B22: Clearance, separation and tactical trajectory change | C22: The NAS should choose, among the maneuvers that restore separation, the one with the lowest impact on the aircraft involved. | D22: Performance (goal) | E22: improved | F22: SN-AIR-05, SN-ENV-01 | G22: ATC decision support; Air traffic control | H22: HLR-ATC-05 | I22: Analysis | J22: TBD | K22: inStudy | L22: draft | M22: [B] | N22: schultz2012adaptiveClimb; mori2022massCruise; kirwan2001coraStrategies | O22: A goal, not a requirement (owner, hand review 2026-10-10). Re-worded by the owner on 2026-10-11: 'impact' replaces 'combined cost' because it is generic and leaves what counts to each controller, and 'with the same number of control instructions' is struck. The held sources agree it is not a duty: the controller's aim is to separate aircraft 'first safely, and then expeditiously' (kirwan2001coraStrategies, p. 4). Not pursued today, because the deciding party lacks the information in SLR-INF-02. In the study: the experiment has to pick one measure of impact to score with; it uses fuel cost plus cost index times time (mori2022massCruise), which is the experiment's choice and not part of this goal. Owner (hand review 2026-10-20): the measure is 'TBD', so the Measure is left TBD here; the experiment's scoring choice stays on HLR-ATC-05.
A23: SLR-CLR-14 | B23: Clearance, separation and tactical trajectory change | C23: The NAS shall keep civil aircraft out of special use airspace while it is active, unless the using agency releases it. | D23: Functional | E23: baseline | F23: SN-MIL-01 | G23: Air traffic control | I23: Inspection | K23: outOfStudy | L23: draft | M23: [C] | N23: faa2025jo711065bb | O23: Restored as out of study (D-031): the owner's hand review of 2026-10-20 keeps every stakeholder requirement of the first draft and makes the cut at the sub-system (HLR) tier. Text as on the 2026-10-10 print. Struck 2026-10-10: 'Not Relevant.' It has no HLR: the study does not depend on it.
A24: SLR-CLR-15 | B24: Clearance, separation and tactical trajectory change | C24: The NAS shall keep the control instructions needed to resolve a conflict within what the sector team can sustain. | D24: Performance | E24: baseline | F24: SN-ATC-04 | G24: Air traffic control | H24: HLR-ATC-06 | I24: Analysis | J24: instructions issued plus follow-up instructions, per conflict (count) | K24: inStudy | L24: draft | M24: [B] | N24: rantanen2012conflictManeuvers; kirwan2001coraStrategies | O24: New, proposed by Claude on 2026-10-11 so that the restored SN-ATC-04 has an answer; not written by the owner. It replaces the struck goal SLR-CLR-12 (fewest instructions), which the owner rejected: instruction count is not a safety objective, and a controller who is not overworked can give as many as wanted. So the count is a ceiling. No ceiling is set, because no held source gives one. In the study: the experiment's workload column (instructions issued plus follow-ups). Accepted by the owner as worded ('ok', hand review 2026-10-20).
A25: SLR-INF-01 | B25: Information for trajectory decisions | C25: The NAS shall give the sector controller the filed route, requested altitude and requested speed of each aircraft before it enters the sector. | D25: Interface | E25: baseline | F25: SN-ATC-01, SN-ATC-03 | G25: Air traffic control; En-route center (ARTCC) | H25: HLR-ATC-03 | I25: Inspection | K25: inStudy | L25: draft | M25: [A] | N25: faa2025jo711065bb | O25: In the study: this is what the controller knows about each aircraft today (case A of the experiment). Owner (hand review 2026-10-20), on 'sector controller': 'modeled?' Not as its own part: airspaceManagement.atc stands for the controllers, and the allocation names it and the en-route center. Open question.
A26: SLR-INF-02 | B26: Information for trajectory decisions | C26: The NAS shall give the party that decides a change to an aircraft's trajectory the information needed to preserve safety and pursue optimality. | D26: Interface | E26: improved | F26: SN-AIR-05, SN-CRW-03 | G26: Flight management system; Airline operations center; ATC decision support; Air traffic control | H26: HLR-OPS-05, HLR-ATC-08, HLR-ACF-05 | I26: Analysis | K26: inStudy | L26: draft | M26: [B] | N26: schultz2012adaptiveClimb; coppenbarger1999climbPrediction; sheth2010creditsConcept | O26: Owner's wording (hand review 2026-10-10). It replaces three statements that named gross weight, cost index and connection priority one at a time (the first draft's SLR-INF-02, SLR-INF-03 and SLR-INF-04); the owner judged them implied. Those three items are the attributes of AirlinePerformanceShare in nas_sysml_package_definitions.sysml (D-019) and are where the next tier of requirements starts. Not met today: the controller does not receive weight or cost index (schultz2012adaptiveClimb, page 2). Cases C and D of the experiment.
A27: SLR-INF-05 | B27: Information for trajectory decisions | C27: The NAS shall disclose an airline's shared weight, cost index and connection priority only to the parties deciding that flight's trajectory. | D27: Constraint | E27: baseline | F27: SN-AIR-06 | G27: Air traffic control; Command Center (ATCSCC) | I27: Inspection | K27: outOfStudy | L27: draft | M27: [B] | N27: schultz2012adaptiveClimb | O27: Restored as out of study (D-031): the owner's hand review of 2026-10-20 keeps every stakeholder requirement of the first draft and makes the cut at the sub-system (HLR) tier. Text as on the 2026-10-10 print. Struck 2026-10-10: 'Maybe not needed if exposed as API.' Carried as an assumption (D-020 item 4). It has no HLR: the study does not depend on it.
A28: SLR-INF-06 | B28: Information for trajectory decisions | C28: The NAS shall give the dispatcher and the flight crew the reported and forecast weather and turbulence along the planned route. | D28: Interface | E28: baseline | F28: SN-PAX-03, SN-CRW-02 | G28: Airline operations center; Flight deck crew | I28: Inspection | K28: outOfStudy | L28: draft | M28: [C] | N28: seamster2011collabSystems | O28: Restored as out of study (D-031): the owner's hand review of 2026-10-20 keeps every stakeholder requirement of the first draft and makes the cut at the sub-system (HLR) tier. Text as on the 2026-10-10 print. '+ weather' added by the owner 2026-10-10; struck 2026-10-11: 'Not relevant to my study. Winds & weather should be factored into account by controllers, but that's not a SLR.' It has no HLR: the study does not depend on it.
A29: SLR-INF-07 | B29: Information for trajectory decisions | C29: The NAS shall send the airline and the destination airport an updated arrival estimate whenever a flight's estimate changes by more than 5 minutes. | D29: Interface | E29: baseline | F29: SN-AIR-02, SN-AIR-03, SN-APT-01 | G29: Flight management system; Flight deck crew; Airline operations center; Airport management system | H29: HLR-CRW-04, HLR-OPS-06 | I29: Inspection | J29: change in estimated arrival time that triggers an update (minutes). Value: 5 | K29: inStudy | L29: draft | M29: [B] | N29: seamster2011collabSystems | O29: In the study: how the airline learns what a trajectory change did to the arrival time. It answers SN-AIR-03 together with SLR-CLR-04: the crew and the dispatcher coordinate over that path, and this is what they pass. The 5 minutes is the crew-to-dispatch practice in seamster2011collabSystems (survey item: notify dispatch of ETA changes greater than 5 minutes). Extending the same trigger to the airport is this draft's proposal, not the source's.
A30: SLR-EXE-01 | B30: Onboard execution | C30: The NAS shall hold each flight's cleared route and altitudes in the flight management system as the path the aircraft's guidance follows. | D30: Functional | E30: baseline | F30: SN-ATC-03 | G30: Flight management system | I30: Inspection | K30: outOfStudy | L30: draft | M30: [SME] | O30: Restored as out of study (D-031): the owner's hand review of 2026-10-20 keeps every stakeholder requirement of the first draft and makes the cut at the sub-system (HLR) tier. Text as on the 2026-10-10 print. Struck 2026-10-10: 'why needed?' It has no HLR: the study does not depend on it.
A31: SLR-EXE-02 | B31: Onboard execution | C31: The NAS shall fly each aircraft along its cleared route and at its cleared altitude and speed within the navigation and altitude tolerances of the airspace. | D31: Performance | E31: baseline | F31: SN-ATC-01, SN-ATC-03 | G31: Auto flight control system; Flight management system | H31: HLR-CRW-01, HLR-ATC-01, HLR-ACF-02 | I31: Analysis | J31: cross-track distance from the cleared route; difference from the cleared altitude (NM and ft) | K31: inStudy | L31: draft | M31: [SME] | O31: Owner (hand review 2026-10-10): this has to be accounted for in the separation requirements. In the study: how far an aircraft may stray from its clearance is part of the margin a resolution must leave. 'And speed' was added by the owner (hand review 2026-10-11); no speed tolerance is named yet. No tolerance is set; it depends on the navigation specification of the route, which the scenario has not chosen.
A32: SLR-EXE-03 | B32: Onboard execution | C32: The NAS shall predict each flight's arrival time, fuel at destination, optimum altitude and maximum altitude from the aircraft's estimated performance. | D32: Functional | E32: baseline | F32: SN-AIR-01, SN-CRW-03 | G32: Flight management system; AOC decision support | H32: HLR-CRW-03, HLR-CRW-05, HLR-ACF-01, HLR-ACF-05 | I32: Inspection | K32: inStudy | L32: draft | M32: [SME] | N32: mori2022massCruise | O32: 'Estimated performance' is the owner's wording. 'On board' was struck by the owner (hand review 2026-10-11: 'Why on-board? This info is what factors into the FL350 number'): the prediction matters wherever it is made, and it is what sits behind the rule in D-013 that a climb is offered only at or below FL350. On board it is the item FmsPerformancePrediction in nas_sysml_package_definitions.sysml. The airline's flight planning system was added to the allocation by Claude for the same reason.
A33: SLR-EXE-04 | B33: Onboard execution | C33: The NAS shall change an aircraft's flown trajectory only through flight deck controls operated by the flight crew. | D33: Constraint | E33: baseline | F33: SN-CRW-01, SN-GOV-02 | G33: Flight deck controls; Flight deck crew | I33: Inspection | K33: outOfStudy | L33: draft | M33: [SME] | N33: 14 CFR 91.3 | O33: Restored as out of study (D-031): the owner's hand review of 2026-10-20 keeps every stakeholder requirement of the first draft and makes the cut at the sub-system (HLR) tier. Text as on the 2026-10-10 print. Struck 2026-10-10: 'of course. Why needed?' It has no HLR: the study does not depend on it.
A34: SLR-EXE-06 | B34: Onboard execution | C34: The NAS shall alert the flight crew, dispatchers and controllers when the fuel predicted at the destination falls below the required reserve. | D34: Functional | E34: baseline | F34: SN-GOV-01, SN-CRW-03, SN-PAX-01, SN-CRW-02 | G34: Flight management system; Dispatcher; Air traffic control | H34: HLR-CRW-04, HLR-OPS-06, HLR-ACF-03 | I34: Inspection | K34: inStudy | L34: draft | M34: [SME] | O34: 'Dispatchers and controllers' was added by the owner (hand review 2026-10-11). In the study: fuel at the destination is a limit on which resolution an aircraft can accept. The dispatcher and air traffic control were added to the allocation by Claude to match. Whether a controller is alerted this way today was not checked against a source, so the baseline tag is unconfirmed.
A35: SLR-APT-01 | B35: Airport and surface | C35: The NAS shall assign each arriving flight a gate before it lands. | D35: Functional | E35: baseline | F35: SN-APT-01, SN-AIR-02 | G35: Airport management system | I35: Demonstration | K35: outOfStudy | L35: draft | M35: [C] | O35: Restored as out of study (D-031): the owner's hand review of 2026-10-20 keeps every stakeholder requirement of the first draft and makes the cut at the sub-system (HLR) tier. Text as on the 2026-10-10 print. Struck 2026-10-10: 'Not relevant'. It has no HLR: the study does not depend on it.
A36: SLR-APT-02 | B36: Airport and surface | C36: The NAS shall sequence arrivals and departures so that each runway is used at its declared capacity whenever demand is at or above that rate. | D36: Performance | E36: baseline | F36: SN-APT-02, SN-ATC-02 | G36: Terminal approach control (TRACON); Control tower | I36: Analysis | J36: runway operations per hour against the declared rate (operations per hour) | K36: outOfStudy | L36: draft | M36: [A] | N36: faa2025jo72103ee | O36: Restored as out of study (D-031): the owner's hand review of 2026-10-20 keeps every stakeholder requirement of the first draft and makes the cut at the sub-system (HLR) tier. Text as on the 2026-10-10 print. 'Capacity' for 'rate' by the owner 2026-10-10 ('Not necessary... but informs prioritization decisions'); struck 2026-10-11: 'Remove.' It has no HLR: the study does not depend on it.
A37: SLR-APT-03 | B37: Airport and surface | C37: The NAS shall hold a flight that has a known departure delay at its gate with engines off, not in a taxiway queue. | D37: Functional | E37: baseline | F37: SN-APT-03, SN-ENV-01 | G37: Control tower; Airline operations center | I37: Demonstration | K37: outOfStudy | L37: draft | M37: [C] | O37: Restored as out of study (D-031): the owner's hand review of 2026-10-20 keeps every stakeholder requirement of the first draft and makes the cut at the sub-system (HLR) tier. Text as on the 2026-10-10 print. Struck 2026-10-10: 'I didn't list this, as the SME. Ground delay isn't my focus!' It has no HLR: the study does not depend on it.
A38: SLR-APT-04 | B38: Airport and surface | C38: The NAS shall have each aircraft fuelled, loaded and sealed by its scheduled off- block time. | D38: Performance | E38: baseline | F38: SN-AIR-02 | G38: Ground handling; Fuel distribution system; Flight deck crew | H38: HLR-APT-01, HLR-APT-02 | I38: Demonstration | J38: actual off-block time minus scheduled off-block time (minutes) | K38: inStudy | L38: draft | M38: [B] | N38: schultz2017turnaround | O38: Owner (hand review 2026-10-10): this speaks to the unknowns in weights and to when the information is available. The final weight is known only when loading ends. 'Sealed' replaces 'closed up' (owner).
A39: SLR-APT-05 | B39: Airport and surface | C39: The NAS shall assign departure and arrival procedures that follow the airport's published noise abatement procedures. | D39: Constraint | E39: baseline | F39: SN-ENV-02 | G39: Control tower; Terminal approach control (TRACON); Dispatcher | I39: Inspection | K39: outOfStudy | L39: draft | M39: [B] | N39: seamster2011collabSystems | O39: Restored as out of study (D-031): the owner's hand review of 2026-10-20 keeps every stakeholder requirement of the first draft and makes the cut at the sub-system (HLR) tier. Text as on the 2026-10-10 print. Struck 2026-10-10: 'Not needed.' It has no HLR: the study does not depend on it.
A40: SLR-MEA-01 | B40: Measurement and records | C40: The NAS shall record each change to an aircraft's trajectory, to its clearance, or to the constraints imposed on it, with the authority that issued it and the time. | D40: Functional | E40: baseline | F40: SN-GOV-01, SN-GOV-02 | G40: Dispatcher; Air traffic control; Command Center (ATCSCC) | H40: HLR-ATC-09 | I40: Inspection | K40: inStudy | L40: draft | M40: [A] | N40: faa2025jo72103ee | O40: Re-worded from the owner's note (hand review 2026-10-10) and left standing in the second review. In the study: the record is what lets a resolution be scored after the fact.
A41: SLR-MEA-02 | B41: Measurement and records | C41: The NAS shall report the fuel burned and the CO2 emitted by each flight, at 3.16 kg of CO2 per kg of fuel. | D41: Performance | E41: baseline | F41: SN-ENV-01, SN-AIR-01 | G41: Flight management system; Airline operations center | H41: HLR-OPS-07 | I41: Analysis | J41: CO2 emitted per kg of fuel burned (kg CO2 per kg fuel). Value: 3.16 | K41: inStudy | L41: draft | M41: [A] | N41: icao2024icecMethodology | O41: In the study: the experiment's fuel column, and the CO2 figure derived from it. icao2024icecMethodology page 6, accepted in D-015. The number is a conversion factor, not a limit.
A42: SLR-MEA-03 | B42: Measurement and records | C42: The NAS shall report each flight's gate arrival time against its scheduled arrival time. | D42: Functional | E42: baseline | F42: SN-AIR-02, SN-PAX-02 | G42: Airline operations center | I42: Analysis | J42: gate arrival time minus scheduled arrival time (minutes) | K42: outOfStudy | L42: draft | M42: [C] | O42: Restored as out of study (D-031): the owner's hand review of 2026-10-20 keeps every stakeholder requirement of the first draft and makes the cut at the sub-system (HLR) tier. Text as on the 2026-10-10 print. Struck 2026-10-10: 'Relevance?' It has no HLR: the study does not depend on it.
A43: SLR-MEA-04 | B43: Measurement and records | C43: The NAS shall report the delay each flight received from traffic management initiatives, by airline. | D43: Functional | E43: baseline | F43: SN-ATC-05 | G43: Command Center (ATCSCC) | I43: Analysis | J43: assigned delay per flight (minutes) | K43: outOfStudy | L43: draft | M43: [C] | O43: Restored as out of study (D-031): the owner's hand review of 2026-10-20 keeps every stakeholder requirement of the first draft and makes the cut at the sub-system (HLR) tier. Text as on the 2026-10-10 print. Struck 2026-10-10 with no mark: it existed only so SLR-FLW-05 could be checked. It has no HLR: the study does not depend on it.

Sheet Sub-system HLRs
A1: ID | B1: Constituent system | C1: Requirement | D1: Objective | E1: Kind | F1: State | G1: Comes from | H1: Allocated to | I1: Means | J1: Check | K1: Measure | L1: Scope | M1: Status | N1: Basis | O1: Evidence | P1: Rationale (from the model) | Q1: Review notes
A2: HLR-CRW-01 | B2: Flight crew | C2: The flight crew shall safely control the flight from origin to destination, as cleared by air traffic control with or without negotiation, and in collaboration with flight operations. | D2: The aircraft flies the trajectory that was cleared, and only that one, unless safety requires otherwise. | E2: Functional | F2: baseline | G2: SLR-EXE-02, SLR-CLR-08, SLR-PLN-05 | H2: Flight deck crew | J2: Demonstration | L2: inStudy | M2: draft | N2: [SME] | O2: 14 CFR 91.3 | P2: The owner's sentence (2026-10-11), with 'cleared by' for 'cleared with'. In the study: whatever resolution is chosen, it takes effect only when the crew flies it.
A3: HLR-CRW-02 | B3: Flight crew | C3: The flight crew shall accept a clearance only if the aircraft can fly it, and shall answer 'unable' when it cannot. | D3: No clearance the aircraft cannot fly is flown. | E3: Functional | F3: baseline | G3: SLR-CLR-10 | H3: Flight deck crew | J3: Demonstration | L3: inStudy | M3: draft | N3: [B] | O3: coppenbarger1999climbPrediction | P3: In the study: this is how today's NAS catches a climb the aircraft is too heavy for. It costs a refused clearance and a second one, which the experiment counts as extra instructions.
A4: HLR-CRW-03 | B4: Flight crew | C4: The flight crew shall ask air traffic control for a change of route, altitude or speed when the crew deems it beneficial, optionally in collaboration with the dispatcher. | D4: What the aircraft knows about its own best altitude and speed reaches the controller. | E4: Functional | F4: baseline | G4: SLR-CLR-09, SLR-EXE-03 | H4: Flight deck crew | J4: Demonstration | L4: inStudy | M4: draft | N4: [B] | O4: engility2014tasarAlaska | P4: In the study: a crew request is the only channel for this knowledge today, so it is what the proposed data share is compared with. Owner (hand review 2026-10-20): 'Why call out FMS?' The trigger is now the crew's judgement, optionally with dispatch (owner's words).
A5: HLR-CRW-04 | B5: Flight crew | C5: The flight crew shall tell the dispatcher of each change to the cleared trajectory. | D5: The airline learns of a tactical intervention in time to re-plan. | E5: Interface | F5: baseline | G5: SLR-INF-07, SLR-EXE-06, SLR-CLR-04 | H5: Flight deck crew | J5: Inspection | L5: inStudy | M5: draft | N5: [B] | O5: seamster2011collabSystems | P5: Owner (2026-10-11): the crew and the dispatchers are the ones who have to coordinate for the airline to be informed (SN-AIR-03). Owner (hand review 2026-10-20) struck the trigger (arrival time moved by more than 5 minutes, or fuel at the destination below the reserve) and ended the sentence: 'Period?' The 5-minute trigger stays on the parent SLR-INF-07 (seamster2011collabSystems). In the study: this is how the cost of a resolution becomes known to the airline that bears it.
A6: HLR-CRW-05 | B6: Flight crew | C6: The flight crew shall enter the load sheet weights and the released cost index into the flight management system before departure. | D6: The flight management system predicts from the weight the aircraft actually has. | E6: Functional | F6: baseline | G6: SLR-PLN-07, SLR-EXE-03 | H6: Flight deck crew | J6: Inspection | L6: inStudy | M6: draft | N6: [SME] | P6: Graded [SME] for the owner to confirm from industry experience. In the study: the actual weight exists on board because the crew puts it there; it is the figure the high-fidelity means would share. Owner (hand review 2026-10-20): 'EPP gives weight, if available. Dispatch has final fuel numbers, I believe, and planned burn.' That is, the ADS-C extended projected profile can carry the weight to the ground, and the dispatcher already holds the final fuel figures and the planned burn, so the weight need not come only from the crew's entry.
A7: HLR-OPS-01 | B7: Flight operations | C7: Flight operations shall plan each flight's route, cruise altitude, cruise speed and fuel load from a model of the performance of the aircraft assigned to it, with the fuel reserve the operating rules require. | D7: Each aircraft enters cruise at an altitude, speed and weight chosen for that aircraft. | E7: Functional | F7: baseline | G7: SLR-PLN-01, SLR-PLN-02, SLR-PLN-04 | H7: AOC decision support; Dispatcher; Load planner | I7: rule of thumb (A); low-fidelity model (B); high-fidelity model (C) | J7: Analysis | L7: inStudy | M7: draft | N7: [B] | O7: mori2022massCruise; berry2011aocActors | P7: Owner (hand review 2026-10-11): the performance model can be a rule of thumb per aircraft type, a low-fidelity model or a high-fidelity model, and the fuel reserve goes into the low-fidelity model's assumptions. The three are listed as means. The experiment does not score them here: it takes each aircraft's plan as given. In the study: the plan sets the level, speed and weight each aircraft has when the conflict occurs.
A8: HLR-OPS-02 | B8: Flight operations | C8: The dispatcher shall file each flight's plan with air traffic control before departure. | D8: The controller has the airline's intended route, altitude and speed. | E8: Interface | F8: baseline | G8: SLR-PLN-06 | H8: Dispatcher | J8: Inspection | L8: inStudy | M8: draft | N8: [A] | O8: faa2025aim; faa2025jo72103ee | P8: In the study: the filed plan is all the controller knows of the airline's intent today. It is what the rule of thumb and the low-fidelity means decide with.
A9: HLR-OPS-03 | B9: Flight operations | C9: Flight operations shall give the flight crew the dispatch release, flight plan, weather, notices to airmen (NOTAMs) and load sheet before departure. | D9: The crew and the flight management system start from the plan and the actual weights. | E9: Interface | F9: baseline | G9: SLR-PLN-07 | H9: Dispatcher; Load planner | J9: Inspection | L9: inStudy | M9: draft | N9: [B] | O9: seamster2011collabSystems | P9: In the study: the load sheet is where the actual weight enters the aircraft.
A10: HLR-OPS-04 | B10: Flight operations | C10: The dispatcher shall release a flight only with the captain's agreement that it can be flown safely as planned. | D10: The planned cruise level is one the dispatcher and the captain have both agreed the aircraft can fly. | E10: Functional | F10: baseline | G10: SLR-PLN-05 | H10: Dispatcher | J10: Inspection | L10: inStudy | M10: draft | N10: [A] | O10: 14 CFR 121.533 | P10: Owner (2026-10-11): there is no question that a descent can be achieved; a climb is different, and the joint release is what leads to that conclusion in the rule-of-thumb case. The released plan vouches for the planned level and below, and for nothing above it. In the study: this is the reason the rule of thumb descends and does not climb.
A11: HLR-OPS-05 | B11: Flight operations | C11: Flight operations shall make each flight's current gross weight, performance model, relative cost of flight time and connection priority available to the party that decides a change to that flight's trajectory. | D11: The party deciding can tell what each aircraft can fly and what a change costs its airline. | E11: Interface | F11: improved | G11: SLR-INF-02 | H11: Airline operations center | J11: Analysis | L11: inStudy | M11: draft | N11: [B] | O11: schultz2012adaptiveClimb; coppenbarger1999climbPrediction; sheth2010creditsConcept | P11: The three items the first draft listed one at a time and SLR-INF-02 absorbed. They are the attributes of AirlinePerformanceShare in nas_sysml_package_definitions.sysml (D-019). Not done today (schultz2012adaptiveClimb, page 2). In the study: this is what separates the high-fidelity means (weight and cost index, case C; plus connection priority, case D) from the other two. Confidentiality is an assumption (D-020). Owner (hand review 2026-10-20): 'Also it's performance model. Abstract from CI & talk about a measure of the relative cost of flight time?' Cost index is one such measure. AirlinePerformanceShare still names costIndex and carries the model references unexercised (D-019); it was not changed. Applied from a question on the owner's hand review of 2026-10-20; for the owner to confirm (D-031).
A12: HLR-OPS-06 | B12: Flight operations | C12: The dispatcher shall re-plan the flight with its crew when a trajectory change puts the arrival time, the fuel at the destination or flight safety at risk. | D12: A tactical intervention is absorbed by the airline's plan and not only by the one flight. | E12: Functional | F12: baseline | G12: SLR-CLR-04, SLR-INF-07, SLR-EXE-06 | H12: Dispatcher | J12: Demonstration | L12: inStudy | M12: draft | N12: [B] | O12: seamster2011collabSystems | P12: The dispatcher's half of the coordination the owner named for SN-AIR-03 (2026-10-11); HLR-CRW-04 is the crew's half. In the study: context for case D, where a late flight with connections is the reason one aircraft's time is worth more than its fuel. 'Or flight safety' added by the owner (hand review 2026-10-20).
A13: HLR-OPS-07 | B13: Flight operations | C13: Flight operations shall report each flight's fuel burned and its CO2 emitted at 3.16 kg of CO2 per kg of fuel. | D13: The fuel and CO2 effect of a trajectory change can be counted. | E13: Performance | F13: baseline | G13: SLR-MEA-02 | H13: Airline operations center | J13: Analysis | K13: CO2 emitted per kg of fuel burned (kg CO2 per kg fuel). Value: 3.16 | L13: inStudy | M13: draft | N13: [A] | O13: icao2024icecMethodology | P13: In the study: the experiment's fuel column and the CO2 figure derived from it (D-015).
A14: HLR-ATC-01 | B14: Air traffic control | C14: Air traffic control shall keep each pair of aircraft it controls separated by at least the applicable minimum, allowing for each aircraft's permitted deviation from its cleared route, altitude and speed. | D14: No loss of separation. | E14: Performance | F14: baseline | G14: SLR-CLR-01, SLR-EXE-02 | H14: Air traffic control; En-route center (ARTCC) | J14: Analysis | K14: lateral and vertical distance between each pair of aircraft (NM and ft) | L14: inStudy | M14: draft | N14: [A] | O14: faa2025jo711065bb | P14: Owner (hand review 2026-10-10): conformance has to be accounted for in the separation requirements. In the study: the hard constraint on every resolution option, whichever means chooses it.
A15: HLR-ATC-02 | B15: Air traffic control | C15: ATC decision support shall alert the sector controller to each predicted loss of separation before it occurs. | D15: The controller has time to choose a resolution and not only to react. | E15: Functional | F15: baseline | G15: SLR-CLR-02 | H15: ATC decision support | J15: Analysis | L15: inStudy | M15: draft | N15: [B] | O15: engility2014tasarAlaska | P15: In the study: the starting event of the experiment. No look-ahead time is set; engility2014tasarAlaska page 9 uses eight minutes in its own model.
A16: HLR-ATC-03 | B16: Air traffic control | C16: The en-route center shall inform the sector controller of each aircraft's filed route, requested altitude and requested speed before the aircraft enters the sector. | D16: The controller knows where each aircraft intends to go. | E16: Interface | F16: baseline | G16: SLR-INF-01 | H16: En-route center (ARTCC) | J16: Inspection | L16: inStudy | M16: draft | N16: [A] | O16: faa2025jo711065bb | P16: In the study: together with type, level and speed, this is the whole of 'today's information' that the rule of thumb decides with (case A). 'Inform ... of' for 'show' by the owner (hand review 2026-10-20).
A17: HLR-ATC-04 | B17: Air traffic control | C17: Air traffic control shall resolve each predicted conflict with a clearance that every aircraft it moves can fly. | D17: The conflict is resolved by the first clearance issued, with no 'unable' and no second attempt. | E17: Constraint | F17: improved | G17: SLR-CLR-10, SLR-CLR-01 | H17: Air traffic control; ATC decision support | I17: rule of thumb (A); low-fidelity model (B); high-fidelity model (C); high-fidelity model plus connections (D). Scored. | J17: Analysis | K17: whether the chosen option is flyable under the truth model (yes or no) | L17: inStudy | M17: draft | N17: [B] | O17: coppenbarger1999climbPrediction; engility2014tasarAlaska | P17: Four means of knowing what an aircraft can fly, scored in the experiment. Rule of thumb: descend, and offer a climb only at or below FL350 (D-013, from engility2014tasarAlaska page 8; the joint release in HLR-OPS-04 is why a descent is safe to assume). Low-fidelity model: one nominal weight per aircraft type (coppenbarger1999climbPrediction). High-fidelity model: each aircraft's own weight, shared under HLR-OPS-05. The fourth adds connection priority, which does not change what can be flown. The truth model's thrust check (NasAnalysis::CanHoldLevel) says whether the option each means chose was flyable.
A18: HLR-ATC-05 | B18: Air traffic control | C18: Air traffic control should choose, among the clearances that resolve a conflict and can be flown, the one with the lowest impact on the systems involved. | D18: Lowest impact on the systems involved. The experiment scores impact as fuel burned and as airline cost (fuel cost plus cost index times time), per aircraft and summed. | E18: Performance (goal) | F18: improved | G18: SLR-CLR-13 | H18: ATC decision support; Air traffic control | I18: rule of thumb (A); low-fidelity model (B); high-fidelity model (C); high-fidelity model plus connections (D). Scored. | J18: Analysis | K18: fuel burned and airline cost, per aircraft and summed over the aircraft involved (kg and USD per conflict) | L18: inStudy | M18: draft | N18: [B] | O18: schultz2012adaptiveClimb; mori2022massCruise; kirwan2001coraStrategies | P18: A goal, like its parent SLR-CLR-13. Four means of judging impact, scored in the experiment. Rule of thumb: one descent, by the controller's rule (rantanen2012conflictManeuvers: 23 of 36 observed cases). Low-fidelity model: lowest estimated cost with one nominal weight per type, which cannot tell two aircraft of one type apart. High-fidelity model: lowest estimated cost with each aircraft's own weight and cost index. High-fidelity model plus connections: the same, with the airline's connection priority. One truth model scores what each means chose. Owner (hand review 2026-10-20) circled 'aircraft': 'systems?' The parent SLR-CLR-13 still says 'the aircraft involved'. Applied from a question on the owner's hand review of 2026-10-20; for the owner to confirm (D-031).
A19: HLR-ATC-06 | B19: Air traffic control | C19: Air traffic control shall resolve each predicted conflict within the number of instructions the sector team can sustain. | D19: Controller workload stays under its ceiling whichever means chooses the resolution. | E19: Performance | F19: baseline | G19: SLR-CLR-15 | H19: Air traffic control | I19: rule of thumb (A); low-fidelity model (B); high-fidelity model (C); high-fidelity model plus connections (D). Scored. | J19: Analysis | K19: instructions issued plus follow-up instructions, per conflict (count) | L19: inStudy | M19: draft | N19: [B] | O19: rantanen2012conflictManeuvers; kirwan2001coraStrategies | P19: No ceiling is set, as on the parent SLR-CLR-15, so the experiment reports the count for each means and does not pass or fail it. In the study: the experiment's workload column, which is how a cheaper resolution that takes more instructions is shown for what it is.
A20: HLR-ATC-07 | B20: Air traffic control | C20: Air traffic control shall answer each flight crew request for a route, altitude or speed change with an approval, an amended clearance or 'unable'. | D20: A crew request is never left open. | E20: Functional | F20: baseline | G20: SLR-CLR-09 | H20: Air traffic control | J20: Demonstration | L20: inStudy | M20: draft | N20: [A] | O20: faa2025jo711065bb; engility2014tasarAlaska | P20: JO 7110.65BB paragraph 2-1-18, as recorded in evidence/literature-notes/summaries/5 - faa2025jo711065bb.md (which also allows 'stand by'). In the study: the controller's half of the request channel in HLR-CRW-03. Owner (hand review 2026-10-20): 'Confirm ATC unable. I think it's actually deny/negative.' Checked against the summary only: 2-1-18 lists '(request) APPROVED', approved with restrictions, 'UNABLE' (with a reason if time permits) and 'STAND BY'. 'Unable' is kept; the order itself was not re-read.
A21: HLR-ATC-08 | B21: Air traffic control | C21: ATC decision support shall use the best information available to it about each flight, including the gross weight, performance model, relative cost of flight time and connection priority the airline has shared, to judge which clearances the aircraft can fly and what each costs. | D21: The shared information changes the decision and does not only arrive. | E21: Functional | F21: improved | G21: SLR-INF-02 | H21: ATC decision support | J21: Analysis | L21: inStudy | M21: draft | N21: [B] | O21: schultz2012adaptiveClimb; coppenbarger1999climbPrediction | P21: The receiving end of HLR-OPS-05 (D-019: decision support is owned by the system that decides, D-012). Not done today. In the study: the difference between case B and cases C and D. Owner (hand review 2026-10-20): 'Why not use the best information available to them?' Applied from a question on the owner's hand review of 2026-10-20; for the owner to confirm (D-031).
A22: HLR-ATC-09 | B22: Air traffic control | C22: Air traffic control shall record each clearance it issues with the issuing facility and the time. | D22: A resolution can be examined after the fact. | E22: Functional | F22: baseline | G22: SLR-MEA-01 | H22: Air traffic control | J22: Inspection | L22: inStudy | M22: draft | N22: [A] | O22: faa2025jo72103ee | P22: In the study: the record is what a real-world version of the experiment's instruction count would be taken from.
A23: HLR-ACF-01 | B23: Aircraft | C23: The flight management system shall predict the flight's arrival time, fuel at the destination, optimum altitude and maximum altitude from the entered weights, the cost index and the forecast winds. | D23: The aircraft knows what it can fly and what is best for it. | E23: Functional | F23: baseline | G23: SLR-EXE-03 | H23: Flight management system | J23: Inspection | L23: inStudy | M23: draft | N23: [SME] | O23: mori2022massCruise | P23: Graded [SME]. The item FmsPerformancePrediction in nas_sysml_package_definitions.sysml. In the study: the on-board high-fidelity model. Its maximum altitude is the answer the rule of thumb replaces with 'at or below FL350'.
A24: HLR-ACF-02 | B24: Aircraft | C24: The auto flight control system shall hold the aircraft on its cleared route, altitude and speed within the tolerances of the airspace. | D24: The aircraft is where its clearance says it is. | E24: Performance | F24: baseline | G24: SLR-EXE-02 | H24: Auto flight control system; Flight management system | J24: Analysis | K24: cross-track distance from the cleared route; difference from the cleared altitude and speed (NM, ft and Mach) | L24: inStudy | M24: draft | N24: [SME] | P24: Graded [SME]. No tolerance is set. In the study: the deviation HLR-ATC-01 has to allow for.
A25: HLR-ACF-03 | B25: Aircraft | C25: The flight management system shall alert the flight crew when the fuel it predicts at the destination falls below the required reserve. | D25: The crew knows when a trajectory change has used up the fuel margin. | E25: Functional | F25: baseline | G25: SLR-EXE-06 | H25: Flight management system | J25: Inspection | L25: inStudy | M25: draft | N25: [SME] | P25: Graded [SME]. The parent SLR-EXE-06 also names dispatchers and controllers; they hear through the crew (HLR-CRW-04). In the study: fuel at the destination is a limit on which resolution an aircraft can accept.
A26: HLR-ACF-04 | B26: Aircraft | C26: The aircraft communication system shall carry voice and data between the flight crew and both air traffic control and the dispatcher for the whole flight. | D26: Clearances, refusals, requests and reports to the airline can all be exchanged from the flight deck. | E26: Interface | F26: baseline | G26: SLR-CLR-04 | H26: Aircraft communication system | J26: Inspection | L26: inStudy | M26: draft | N26: [SME] | P26: Graded [SME]. In the study: every exchange the experiment counts as an instruction crosses this link.
A27: HLR-ACF-05 | B27: Aircraft | C27: The flight management system shall make its current gross weight and its predicted optimum and maximum altitudes available for sharing with the party that decides, whether through the airline's systems or air traffic control's. | D27: The aircraft's own figures can reach the party that decides, by whichever system carries them (HLR-OPS-05). | E27: Interface | F27: baseline | G27: SLR-INF-02, SLR-EXE-03 | H27: Flight management system; Aircraft communication system | J27: Inspection | L27: inStudy | M27: draft | N27: [SME] | P27: The FMS-to-airline exchange named as one of the three on the thread in D-019 item 4. Whether aircraft do this today is for the owner to say [SME]; it is left as baseline because D-019 tags only the airline-to-ATC exchange as improved. In the study: the first link of the high-fidelity means. Owner (hand review 2026-10-20): 'The GW, CI & perf data can come from the flight and/or dispatch or the same computer system, whether the airline's or ATC's.' Applied from a question on the owner's hand review of 2026-10-20; for the owner to confirm (D-031).
A28: HLR-ACF-06 | B28: Aircraft | C28: The aircraft's surveillance system shall broadcast the aircraft's position, altitude, velocity and identity by ADS-B Out. | D28: The ground system and its conflict probe know where each aircraft is and where it is going. | E28: Interface | F28: baseline | G28: SLR-CLR-02, SLR-CLR-01 | H28: Aircraft surveillance system | J28: Inspection | L28: inStudy | M28: draft | N28: [C] | O28: 14 CFR 91.225 | P28: New. Owner (hand review 2026-10-20), beside HLR-ACF-05: 'Need one HLR for ADS-B data.' In the study: the surveillance input to ResolveConflict (ADS-B position reports, D-030) and the airspace domain's surveillanceIn port. The rule (14 CFR 91.225) is general knowledge, not yet tied to a held source. Wording is Claude's. Applied from a question on the owner's hand review of 2026-10-20; for the owner to confirm (D-031).
A29: HLR-APT-01 | B29: Airport operations | C29: Airport operations shall have each aircraft fuelled, loaded and sealed by its scheduled off-block time. | D29: The flight leaves on schedule with its load complete. | E29: Performance | F29: baseline | G29: SLR-APT-04 | H29: Ground handling; Fuel distribution system | J29: Demonstration | K29: actual off-block time minus scheduled off-block time (minutes) | L29: inStudy | M29: draft | N29: [B] | O29: schultz2017turnaround | P29: In the study: the weakest link of the five systems. It matters only because the weight is not final until loading ends.
A30: HLR-APT-02 | B30: Airport operations | C30: Airport operations shall report the fuel uplifted and the load put on board to the flight crew and the load planner before off-block. | D30: The weight used on board and by the airline is the weight the aircraft has. | E30: Interface | F30: baseline | G30: SLR-APT-04, SLR-PLN-07 | H30: Fuel distribution system; Ground handling | J30: Inspection | L30: inStudy | M30: draft | N30: [C] | P30: D-009 records the fuel slip reaching the crew from the airport fuel carrier; the load report is from general knowledge. In the study: the owner's note on SLR-APT-04, that it speaks to the unknowns in weights and to when the information is available.

Sheet About
A1: Requirements review workbook
A2: Generated 2026-10-22 21:42 from commit d0c723d by tools/export_requirements_xlsx.py.
A3: Source of truth: the .sysml files in projects/nas-sos-capstone/cameo_models/ (D-006). This workbook is a derived copy: mark it up, then apply the changes to the .sysml files and regenerate.
A4: Counts: 30 stakeholder requirements, 42 system requirements, 29 sub-system HLRs. The Coverage sheet counts each by scope and lists any trace gap.
A6: Objectives sheet: reads the other way, from each objective row of knowledge/models/stakeholder-objective-ontology.md to the stakeholder requirements that name it (attribute objectiveRefs), and on to the in-study system requirements and HLRs below them. Bold objective: carried into the study. Grey: carried only by a background or out-of-study requirement. '(no requirement)': no stakeholder requirement names it. Requirements that name no objective row are listed at the end.
A8: How the Decomposition sheet reads
A9: Left to right: stakeholder requirement (SN) -> the system requirements (SLR) that answer it -> the HLRs that come from each SLR. Merged cells span the rows beneath them.
A10: The trace is many-to-many, so an SLR that answers two stakeholder requirements appears under both, marked '(also answers ...)'. An HLR with two parents is marked '(also comes from ...)'.
A11: [IMPROVED] and orange fill: architectureState = improved, something today's NAS does not do (D-018). [GOAL] and italics: obligation = goal, written with 'should' (D-020).
A12: [OUT OF STUDY], grey fill and grey text: studyScope = outOfStudy (D-031). Every stakeholder requirement of the first draft is kept, with the system requirements that answer it; the study's cut is made at the HLR tier, so these stop at the system level with '(no HLR: not carried into the study)'. [BACKGROUND] and lilac fill: a boundary actor's requirement the study holds fixed and uses as input (the operating rules, the CO2 factor). '(no HLR: gap)' in red would be an in-study system requirement with nothing under it.
A14: Review status (from knowledge/models/requirements-and-traceability.md)
A15: In-study stakeholder and system requirements: hand-reviewed by the owner three times (D-020, D-021, D-031). Out-of-study ones: restored on 2026-10-20 from the 10-10 and 10-11 prints with the text they had when struck.
... A17: Every requirement has status = draft. Nothing is baselined.
